{
  "financial": {
    "money": 234210,
    "invoices": [
      {
        "inGameDate": "2023/1/20",
        "perkUsed": 6,
        "moneyBefore": 30000,
        "moneyCost": 2300,
        "moneyAfter": 27700,
        "ability": {
          "normalPower": [
            67.84933968183438,
            72.99425413703753
          ],
          "spin": [
            78.27450784262064,
            81.54578642775918
          ]
        },
        "type": "upgrade",
        "timestamp": "2024-01-15 03:36:23"
      },
      {
        "inGameDate": "2023/1/22",
        "match": "custom_195B277334903CE5+2023+eight_red_pocket_open",
        "moneyBefore": 27700,
        "moneyAfter": 26700,
        "type": "participation",
        "items": [
          {
            "item": "registry",
            "moneyCost": 200
          },
          {
            "item": "travel",
            "moneyCost": 400
          },
          {
            "item": "hotel",
            "moneyCost": 400
          }
        ],
        "timestamp": "2024-01-15 03:36:27"
      },
      {
        "itemType": "tip",
        "item": "primeTipMedium:custom_195B277334903CE5-357",
        "inGameDate": "2023/1/22",
        "moneyBefore": 26700,
        "moneyCost": 80,
        "moneyAfter": 26620,
        "type": "purchase",
        "timestamp": "2024-01-15 03:37:43"
      },
      {
        "itemType": "tip",
        "item": "primeTipMedium:custom_195B277334903CE5-358",
        "inGameDate": "2023/1/22",
        "moneyBefore": 26620,
        "moneyCost": 80,
        "moneyAfter": 26540,
        "type": "purchase",
        "timestamp": "2024-01-15 03:37:49"
      },
      {
        "inGameDate": "2023/1/22",
        "year": 2023,
        "match": "eight_red_pocket_open",
        "moneyBefore": 26540,
        "moneyAfter": 27740,
        "type": "championshipEarn",
        "items": {"TOP_16": {
          "actual": 1200,
          "raw": 1500
        }},
        "timestamp": "2024-01-15 03:52:42"
      },
      {
        "inGameDate": "2023/1/22",
        "moneyBefore": 27740,
        "moneyAfter": 27590,
        "type": "fees",
        "items": [{
          "item": "lifeFee",
          "moneyCost": 150
        }],
        "timestamp": "2024-01-15 03:56:26"
      },
      {
        "inGameDate": "2023/1/25",
        "match": "custom_195B277334903CE5+2023+fresh_hand_open",
        "moneyBefore": 27590,
        "moneyAfter": 24890,
        "type": "participation",
        "items": [
          {
            "item": "registry",
            "moneyCost": 200
          },
          {
            "item": "travel",
            "moneyCost": 2000
          },
          {
            "item": "hotel",
            "moneyCost": 500
          }
        ],
        "timestamp": "2024-01-15 03:56:26"
      },
      {
        "inGameDate": "2023/1/25",
        "match": "pool-half-regular",
        "moneyBefore": 24890,
        "moneyAfter": 24890,
        "type": "challengeEarn",
        "items": {"clearance": {
          "actual": 0,
          "raw": 0
        }},
        "timestamp": "2024-01-15 04:30:15"
      },
      {
        "inGameDate": "2023/1/25",
        "perkUsed": 4,
        "moneyBefore": 24890,
        "moneyCost": 1700,
        "moneyAfter": 23190,
        "ability": {
          "cuePrecision": [
            75.89731600393364,
            77.6614233637763
          ],
          "normalPower": [
            72.99425413703753,
            74.15448397155603
          ],
          "spin": [
            81.54578642775918,
            83.08395497064882
          ],
          "spinControl": [
            74.12440394103386,
            75.95942778339251
          ]
        },
        "type": "upgrade",
        "timestamp": "2024-01-15 04:30:35"
      },
      {
        "itemType": "cue",
        "item": "trashCue2Carbon:custom_195B277334903CE5-360",
        "inGameDate": "2023/1/25",
        "moneyBefore": 23190,
        "moneyCost": 3500,
        "moneyAfter": 19690,
        "type": "purchase",
        "timestamp": "2024-01-15 04:30:52"
      },
      {
        "itemType": "tip",
        "item": "primeTipMedium:custom_195B277334903CE5-361",
        "inGameDate": "2023/1/25",
        "moneyBefore": 19690,
        "moneyCost": 80,
        "moneyAfter": 19610,
        "type": "purchase",
        "timestamp": "2024-01-15 04:31:10"
      },
      {
        "item": "LONG_THINK",
        "inGameDate": "2023/1/25",
        "level": 0,
        "moneyBefore": 19610,
        "moneyAfter": 19810,
        "type": "achievementAward",
        "moneyEarn": 200,
        "timestamp": "2024-01-15 04:31:23"
      },
      {
        "item": "MISCUED",
        "inGameDate": "2023/1/25",
        "level": 0,
        "moneyBefore": 19810,
        "moneyAfter": 20010,
        "type": "achievementAward",
        "moneyEarn": 200,
        "timestamp": "2024-01-15 04:31:24"
      },
      {
        "item": "SHAKE_POCKET",
        "inGameDate": "2023/1/25",
        "level": 0,
        "moneyBefore": 20010,
        "moneyAfter": 20210,
        "type": "achievementAward",
        "moneyEarn": 200,
        "timestamp": "2024-01-15 04:31:24"
      },
      {
        "item": "CUE_BALL_POT",
        "inGameDate": "2023/1/25",
        "level": 0,
        "moneyBefore": 20210,
        "moneyAfter": 20410,
        "type": "achievementAward",
        "moneyEarn": 200,
        "timestamp": "2024-01-15 04:31:24"
      },
      {
        "item": "MISSED_SHOT",
        "inGameDate": "2023/1/25",
        "level": 0,
        "moneyBefore": 20410,
        "moneyAfter": 20610,
        "type": "achievementAward",
        "moneyEarn": 200,
        "timestamp": "2024-01-15 04:31:25"
      },
      {
        "item": "FRAME_NO_ATTACK",
        "inGameDate": "2023/1/25",
        "level": 0,
        "moneyBefore": 20610,
        "moneyAfter": 20810,
        "type": "achievementAward",
        "moneyEarn": 200,
        "timestamp": "2024-01-15 04:31:25"
      },
      {
        "item": "KEY_BALL_FAIL",
        "inGameDate": "2023/1/25",
        "level": 0,
        "moneyBefore": 20810,
        "moneyAfter": 21010,
        "type": "achievementAward",
        "moneyEarn": 200,
        "timestamp": "2024-01-15 04:31:26"
      },
      {
        "item": "WIN_A_FRAME",
        "inGameDate": "2023/1/25",
        "level": 0,
        "moneyBefore": 21010,
        "moneyAfter": 21210,
        "type": "achievementAward",
        "moneyEarn": 200,
        "timestamp": "2024-01-15 04:31:28"
      },
      {
        "item": "WIN_FRAMES",
        "inGameDate": "2023/1/25",
        "level": 0,
        "moneyBefore": 21210,
        "moneyAfter": 21410,
        "type": "achievementAward",
        "moneyEarn": 200,
        "timestamp": "2024-01-15 04:31:28"
      },
      {
        "item": "WIN_A_MATCH",
        "inGameDate": "2023/1/25",
        "level": 0,
        "moneyBefore": 21410,
        "moneyAfter": 21610,
        "type": "achievementAward",
        "moneyEarn": 200,
        "timestamp": "2024-01-15 04:31:28"
      },
      {
        "item": "WIN_FRAMES_NORMAL_DIFFICULTY",
        "inGameDate": "2023/1/25",
        "level": 0,
        "moneyBefore": 21610,
        "moneyAfter": 21810,
        "type": "achievementAward",
        "moneyEarn": 200,
        "timestamp": "2024-01-15 04:31:29"
      },
      {
        "item": "SNOOKER_BREAK_50",
        "inGameDate": "2023/1/25",
        "level": 0,
        "moneyBefore": 21810,
        "moneyAfter": 22010,
        "type": "achievementAward",
        "moneyEarn": 200,
        "timestamp": "2024-01-15 04:31:30"
      },
      {
        "item": "HARD_SNOOKER_BY_OPPONENT",
        "inGameDate": "2023/1/25",
        "level": 0,
        "moneyBefore": 22010,
        "moneyAfter": 22210,
        "type": "achievementAward",
        "moneyEarn": 200,
        "timestamp": "2024-01-15 04:31:31"
      },
      {
        "item": "NOT_RESPECT",
        "inGameDate": "2023/1/25",
        "level": 0,
        "moneyBefore": 22210,
        "moneyAfter": 22410,
        "type": "achievementAward",
        "moneyEarn": 200,
        "timestamp": "2024-01-15 04:31:32"
      },
      {
        "item": "POOL_BREAK_POT",
        "inGameDate": "2023/1/25",
        "level": 0,
        "moneyBefore": 22410,
        "moneyAfter": 22610,
        "type": "achievementAward",
        "moneyEarn": 200,
        "timestamp": "2024-01-15 04:31:34"
      },
      {
        "item": "POOL_BREAK_MASTER",
        "inGameDate": "2023/1/25",
        "level": 0,
        "moneyBefore": 22610,
        "moneyAfter": 22810,
        "type": "achievementAward",
        "moneyEarn": 200,
        "timestamp": "2024-01-15 04:31:35"
      },
      {
        "item": "FIRST_MAIN_OF_TOURNAMENT",
        "inGameDate": "2023/1/25",
        "level": 0,
        "moneyBefore": 22810,
        "moneyAfter": 23010,
        "type": "achievementAward",
        "moneyEarn": 200,
        "timestamp": "2024-01-15 04:31:36"
      },
      {
        "item": "EXPENDITURE",
        "inGameDate": "2023/1/25",
        "level": 0,
        "moneyBefore": 23010,
        "moneyAfter": 23210,
        "type": "achievementAward",
        "moneyEarn": 200,
        "timestamp": "2024-01-15 04:31:38"
      },
      {
        "item": "BUY_ITEMS",
        "inGameDate": "2023/1/25",
        "level": 0,
        "moneyBefore": 23210,
        "moneyAfter": 23410,
        "type": "achievementAward",
        "moneyEarn": 200,
        "timestamp": "2024-01-15 04:31:38"
      },
      {
        "item": "EARNED_MONEY",
        "inGameDate": "2023/1/25",
        "level": 0,
        "moneyBefore": 23410,
        "moneyAfter": 23610,
        "type": "achievementAward",
        "moneyEarn": 200,
        "timestamp": "2024-01-15 04:31:39"
      },
      {
        "inGameDate": "2023/1/25",
        "match": "pool-half-ordered-regular",
        "moneyBefore": 23610,
        "moneyAfter": 23610,
        "type": "challengeEarn",
        "items": {},
        "timestamp": "2024-01-15 04:44:02"
      },
      {
        "inGameDate": "2023/1/25",
        "match": "pool-half-ordered-regular",
        "moneyBefore": 23610,
        "moneyAfter": 23610,
        "type": "challengeEarn",
        "items": {"clearance": {
          "actual": 0,
          "raw": 0
        }},
        "timestamp": "2024-01-15 04:45:23"
      },
      {
        "inGameDate": "2023/1/25",
        "match": "chinese-eight-half-regular",
        "moneyBefore": 23610,
        "moneyAfter": 23610,
        "type": "challengeEarn",
        "items": {"clearance": {
          "actual": 0,
          "raw": 0
        }},
        "timestamp": "2024-01-15 04:46:39"
      },
      {
        "inGameDate": "2023/1/25",
        "perkUsed": 3,
        "moneyBefore": 23610,
        "moneyCost": 1300,
        "moneyAfter": 22310,
        "ability": {
          "rest": [
            70.61218374703745,
            73.5754527222152
          ],
          "normalPower": [
            74.15448397155603,
            75.2683046126938
          ],
          "spin": [
            83.08395497064882,
            84.56059677182287
          ]
        },
        "type": "upgrade",
        "timestamp": "2024-01-15 04:46:54"
      },
      {
        "inGameDate": "2023/1/25",
        "match": "chinese-eight-half-ordered-regular",
        "moneyBefore": 22310,
        "moneyAfter": 22310,
        "type": "challengeEarn",
        "items": {},
        "timestamp": "2024-01-15 04:47:39"
      },
      {
        "inGameDate": "2023/1/25",
        "match": "chinese-eight-half-ordered-regular",
        "moneyBefore": 22310,
        "moneyAfter": 22310,
        "type": "challengeEarn",
        "items": {"clearance": {
          "actual": 0,
          "raw": 0
        }},
        "timestamp": "2024-01-15 04:49:21"
      },
      {
        "inGameDate": "2023/1/25",
        "perkUsed": 4,
        "moneyBefore": 22310,
        "moneyCost": 2000,
        "moneyAfter": 20310,
        "ability": {
          "rest": [
            73.5754527222152,
            76.36092555888229
          ],
          "normalPower": [
            75.2683046126938,
            76.33757242818605
          ],
          "spin": [
            84.56059677182287,
            85.97817290094996
          ],
          "spinControl": [
            75.95942778339251,
            77.72105067205682
          ]
        },
        "type": "upgrade",
        "timestamp": "2024-01-15 04:49:37"
      },
      {
        "inGameDate": "2023/1/25",
        "match": "snooker-clear-color-regular",
        "moneyBefore": 20310,
        "moneyAfter": 20310,
        "type": "challengeEarn",
        "items": {"clearance": {
          "actual": 0,
          "raw": 0
        }},
        "timestamp": "2024-01-15 04:51:15"
      },
      {
        "inGameDate": "2023/1/25",
        "match": "pool-full-regular",
        "moneyBefore": 20310,
        "moneyAfter": 20310,
        "type": "challengeEarn",
        "items": {"clearance": {
          "actual": 0,
          "raw": 0
        }},
        "timestamp": "2024-01-15 04:54:22"
      },
      {
        "inGameDate": "2023/1/25",
        "perkUsed": 4,
        "moneyBefore": 20310,
        "moneyCost": 2000,
        "moneyAfter": 18310,
        "ability": {
          "cuePrecision": [
            77.6614233637763,
            79.35496642922524
          ],
          "normalPower": [
            76.33757242818605,
            77.3640695310586
          ],
          "spin": [
            85.97817290094996,
            87.33904598491196
          ],
          "spinControl": [
            77.72105067205682,
            79.41220864517454
          ]
        },
        "type": "upgrade",
        "timestamp": "2024-01-15 04:54:36"
      },
      {
        "inGameDate": "2023/1/25",
        "year": 2023,
        "match": "fresh_hand_open",
        "moneyBefore": 18310,
        "moneyAfter": 18310,
        "type": "championshipEarn",
        "items": {"TOP_16": {
          "actual": 0,
          "raw": 0
        }},
        "timestamp": "2024-01-15 05:36:17"
      },
      {
        "inGameDate": "2023/1/25",
        "perkUsed": 4,
        "moneyBefore": 18310,
        "moneyCost": 1900,
        "moneyAfter": 16410,
        "ability": {
          "powerControl": [
            77.62640900418744,
            79.32135264401994
          ],
          "cuePrecision": [
            79.35496642922524,
            80.98076777205624
          ],
          "normalPower": [
            77.3640695310586,
            78.34950674981626
          ],
          "spinControl": [
            79.41220864517454,
            81.03572029936757
          ]
        },
        "type": "upgrade",
        "timestamp": "2024-01-15 05:36:33"
      },
      {
        "inGameDate": "2023/1/25",
        "moneyBefore": 16410,
        "moneyAfter": 16060,
        "type": "fees",
        "items": [{
          "item": "lifeFee",
          "moneyCost": 350
        }],
        "timestamp": "2024-01-15 05:37:14"
      },
      {
        "inGameDate": "2023/2/1",
        "match": "custom_195B277334903CE5+2023+eight_yangjiaping_mid_cup",
        "moneyBefore": 16060,
        "moneyAfter": 15760,
        "type": "participation",
        "items": [
          {
            "item": "registry",
            "moneyCost": 100
          },
          {
            "item": "travel",
            "moneyCost": 200
          },
          {
            "item": "hotel",
            "moneyCost": 0
          }
        ],
        "timestamp": "2024-01-15 05:37:14"
      },
      {
        "inGameDate": "2023/2/1",
        "year": 2023,
        "match": "eight_yangjiaping_mid_cup",
        "moneyBefore": 15760,
        "moneyAfter": 16560,
        "type": "championshipEarn",
        "items": {"TOP_16": {
          "actual": 800,
          "raw": 1000
        }},
        "timestamp": "2024-01-15 05:45:35"
      },
      {
        "item": "POT_A_BALL",
        "inGameDate": "2023/2/1",
        "level": 0,
        "moneyBefore": 16560,
        "moneyAfter": 16760,
        "type": "achievementAward",
        "moneyEarn": 200,
        "timestamp": "2024-01-15 05:45:44"
      },
      {
        "item": "POT_BALLS",
        "inGameDate": "2023/2/1",
        "level": 0,
        "moneyBefore": 16760,
        "moneyAfter": 16960,
        "type": "achievementAward",
        "moneyEarn": 200,
        "timestamp": "2024-01-15 05:45:45"
      },
      {
        "item": "POT_BALLS_REST",
        "inGameDate": "2023/2/1",
        "level": 0,
        "moneyBefore": 16960,
        "moneyAfter": 17160,
        "type": "achievementAward",
        "moneyEarn": 200,
        "timestamp": "2024-01-15 05:45:45"
      },
      {
        "item": "POT_BALLS",
        "inGameDate": "2023/2/1",
        "level": 1,
        "moneyBefore": 17160,
        "moneyAfter": 17660,
        "type": "achievementAward",
        "moneyEarn": 500,
        "timestamp": "2024-01-15 05:45:46"
      },
      {
        "item": "CUMULATIVE_LONG_POTS_1",
        "inGameDate": "2023/2/1",
        "level": 0,
        "moneyBefore": 17660,
        "moneyAfter": 17860,
        "type": "achievementAward",
        "moneyEarn": 200,
        "timestamp": "2024-01-15 05:45:46"
      },
      {
        "item": "THREE_BALLS_IN_A_ROW",
        "inGameDate": "2023/2/1",
        "level": 0,
        "moneyBefore": 17860,
        "moneyAfter": 18060,
        "type": "achievementAward",
        "moneyEarn": 200,
        "timestamp": "2024-01-15 05:45:47"
      },
      {
        "item": "POSITIONING_MASTER",
        "inGameDate": "2023/2/1",
        "level": 0,
        "moneyBefore": 18060,
        "moneyAfter": 18260,
        "type": "achievementAward",
        "moneyEarn": 200,
        "timestamp": "2024-01-15 05:45:47"
      },
      {
        "item": "GAIN_BY_SNOOKER",
        "inGameDate": "2023/2/1",
        "level": 0,
        "moneyBefore": 18260,
        "moneyAfter": 18460,
        "type": "achievementAward",
        "moneyEarn": 200,
        "timestamp": "2024-01-15 05:45:47"
      },
      {
        "item": "SOLVE_SNOOKER_SUCCESS",
        "inGameDate": "2023/2/1",
        "level": 0,
        "moneyBefore": 18460,
        "moneyAfter": 18660,
        "type": "achievementAward",
        "moneyEarn": 200,
        "timestamp": "2024-01-15 05:45:48"
      },
      {
        "item": "ACCURACY_WIN",
        "inGameDate": "2023/2/1",
        "level": 0,
        "moneyBefore": 18660,
        "moneyAfter": 18860,
        "type": "achievementAward",
        "moneyEarn": 200,
        "timestamp": "2024-01-15 05:45:48"
      },
      {
        "item": "DOUBLE_POT",
        "inGameDate": "2023/2/1",
        "level": 0,
        "moneyBefore": 18860,
        "moneyAfter": 19060,
        "type": "achievementAward",
        "moneyEarn": 200,
        "timestamp": "2024-01-15 05:45:49"
      },
      {
        "item": "WIN_MATCHES",
        "inGameDate": "2023/2/1",
        "level": 0,
        "moneyBefore": 19060,
        "moneyAfter": 19260,
        "type": "achievementAward",
        "moneyEarn": 200,
        "timestamp": "2024-01-15 05:45:51"
      },
      {
        "item": "SNOOKER_CUMULATE_SCORE",
        "inGameDate": "2023/2/1",
        "level": 0,
        "moneyBefore": 19260,
        "moneyAfter": 19460,
        "type": "achievementAward",
        "moneyEarn": 200,
        "timestamp": "2024-01-15 05:45:53"
      },
      {
        "item": "POOL_CLEAR",
        "inGameDate": "2023/2/1",
        "level": 0,
        "moneyBefore": 19460,
        "moneyAfter": 19660,
        "type": "achievementAward",
        "moneyEarn": 200,
        "timestamp": "2024-01-15 05:45:54"
      },
      {
        "item": "REMAIN_ONE_MUST_LOSE",
        "inGameDate": "2023/2/1",
        "level": 0,
        "moneyBefore": 19660,
        "moneyAfter": 19860,
        "type": "achievementAward",
        "moneyEarn": 200,
        "timestamp": "2024-01-15 05:45:55"
      },
      {
        "item": "PARTICIPATE_TOURNAMENTS",
        "inGameDate": "2023/2/1",
        "level": 0,
        "moneyBefore": 19860,
        "moneyAfter": 20060,
        "type": "achievementAward",
        "moneyEarn": 200,
        "timestamp": "2024-01-15 05:45:56"
      },
      {
        "item": "MAIN_OF_TOURNAMENTS",
        "inGameDate": "2023/2/1",
        "level": 0,
        "moneyBefore": 20060,
        "moneyAfter": 20260,
        "type": "achievementAward",
        "moneyEarn": 200,
        "timestamp": "2024-01-15 05:45:57"
      },
      {
        "inGameDate": "2023/2/1",
        "moneyBefore": 20260,
        "moneyAfter": 19810,
        "type": "fees",
        "items": [{
          "item": "lifeFee",
          "moneyCost": 450
        }],
        "timestamp": "2024-01-15 05:47:59"
      },
      {
        "inGameDate": "2023/2/10",
        "match": "custom_195B277334903CE5+2023+eight_northeast_open",
        "moneyBefore": 19810,
        "moneyAfter": 18810,
        "type": "participation",
        "items": [
          {
            "item": "registry",
            "moneyCost": 200
          },
          {
            "item": "travel",
            "moneyCost": 400
          },
          {
            "item": "hotel",
            "moneyCost": 400
          }
        ],
        "timestamp": "2024-01-15 05:47:59"
      },
      {
        "inGameDate": "2023/2/10",
        "year": 2023,
        "match": "eight_northeast_open",
        "moneyBefore": 18810,
        "moneyAfter": 38810,
        "type": "championshipEarn",
        "items": {"TOP_4": {
          "actual": 20000,
          "raw": 25000
        }},
        "timestamp": "2024-01-15 06:54:53"
      },
      {
        "item": "SOLVE_SNOOKER_SUCCESS_POT",
        "inGameDate": "2023/2/10",
        "level": 0,
        "moneyBefore": 38810,
        "moneyAfter": 39010,
        "type": "achievementAward",
        "moneyEarn": 200,
        "timestamp": "2024-01-15 06:55:19"
      },
      {
        "item": "CUMULATIVE_LONG_POTS_1",
        "inGameDate": "2023/2/10",
        "level": 1,
        "moneyBefore": 39010,
        "moneyAfter": 39510,
        "type": "achievementAward",
        "moneyEarn": 500,
        "timestamp": "2024-01-15 06:55:35"
      },
      {
        "item": "AROUND_TABLE_POSITION",
        "inGameDate": "2023/2/10",
        "level": 0,
        "moneyBefore": 39510,
        "moneyAfter": 39710,
        "type": "achievementAward",
        "moneyEarn": 200,
        "timestamp": "2024-01-15 06:55:37"
      },
      {
        "item": "MULTI_CUSHION_POSITION_1",
        "inGameDate": "2023/2/10",
        "level": 0,
        "moneyBefore": 39710,
        "moneyAfter": 39910,
        "type": "achievementAward",
        "moneyEarn": 200,
        "timestamp": "2024-01-15 06:55:37"
      },
      {
        "item": "WIN_ALL_MATCHES",
        "inGameDate": "2023/2/10",
        "level": 0,
        "moneyBefore": 39910,
        "moneyAfter": 40110,
        "type": "achievementAward",
        "moneyEarn": 200,
        "timestamp": "2024-01-15 06:55:39"
      },
      {
        "item": "SEMIFINAL_STAGE",
        "inGameDate": "2023/2/10",
        "level": 0,
        "moneyBefore": 40110,
        "moneyAfter": 40310,
        "type": "achievementAward",
        "moneyEarn": 200,
        "timestamp": "2024-01-15 06:55:40"
      },
      {
        "item": "FINAL_FRAME",
        "inGameDate": "2023/2/10",
        "level": 0,
        "moneyBefore": 40310,
        "moneyAfter": 40510,
        "type": "achievementAward",
        "moneyEarn": 200,
        "timestamp": "2024-01-15 06:55:40"
      },
      {
        "item": "POOL_BREAK_CLEAR",
        "inGameDate": "2023/2/10",
        "level": 0,
        "moneyBefore": 40510,
        "moneyAfter": 40710,
        "type": "achievementAward",
        "moneyEarn": 200,
        "timestamp": "2024-01-15 06:55:44"
      },
      {
        "item": "BEST_FOUR",
        "inGameDate": "2023/2/10",
        "level": 0,
        "moneyBefore": 40710,
        "moneyAfter": 40910,
        "type": "achievementAward",
        "moneyEarn": 200,
        "timestamp": "2024-01-15 06:55:47"
      },
      {
        "item": "DEFEAT_UNIQUE_OPPONENTS_CEB",
        "inGameDate": "2023/2/10",
        "level": 0,
        "moneyBefore": 40910,
        "moneyAfter": 41110,
        "type": "achievementAward",
        "moneyEarn": 200,
        "timestamp": "2024-01-15 06:55:49"
      },
      {
        "inGameDate": "2023/2/10",
        "moneyBefore": 41110,
        "moneyAfter": 40390,
        "type": "fees",
        "items": [{
          "item": "lifeFee",
          "moneyCost": 720
        }],
        "timestamp": "2024-01-15 06:58:12"
      },
      {
        "inGameDate": "2023/2/22",
        "perkUsed": 7,
        "moneyBefore": 40390,
        "moneyCost": 3800,
        "moneyAfter": 36590,
        "ability": {
          "rest": [
            76.36092555888229,
            81.44051382382838
          ],
          "powerControl": [
            79.32135264401994,
            80.94849853825914
          ],
          "normalPower": [
            78.34950674981626,
            80.20370542063067
          ],
          "spin": [
            87.33904598491196,
            88.64548414551548
          ],
          "spinControl": [
            81.03572029936757,
            82.59429148739287
          ]
        },
        "type": "upgrade",
        "timestamp": "2024-01-15 06:59:12"
      },
      {
        "inGameDate": "2023/2/22",
        "moneyBefore": 36590,
        "moneyAfter": 36290,
        "type": "fees",
        "items": [{
          "item": "lifeFee",
          "moneyCost": 300
        }],
        "timestamp": "2024-01-15 07:06:21"
      },
      {
        "inGameDate": "2023/2/27",
        "match": "custom_195B277334903CE5+2023+dog_give_power_open",
        "moneyBefore": 36290,
        "moneyAfter": 33390,
        "type": "participation",
        "items": [
          {
            "item": "registry",
            "moneyCost": 500
          },
          {
            "item": "travel",
            "moneyCost": 1600
          },
          {
            "item": "hotel",
            "moneyCost": 800
          }
        ],
        "timestamp": "2024-01-15 07:06:21"
      },
      {
        "item": "POT_BALLS_REST",
        "inGameDate": "2023/2/27",
        "level": 1,
        "moneyBefore": 33390,
        "moneyAfter": 33890,
        "type": "achievementAward",
        "moneyEarn": 500,
        "timestamp": "2024-01-15 07:24:36"
      },
      {
        "item": "WIN_MATCHES",
        "inGameDate": "2023/2/27",
        "level": 1,
        "moneyBefore": 33890,
        "moneyAfter": 34390,
        "type": "achievementAward",
        "moneyEarn": 500,
        "timestamp": "2024-01-15 07:24:38"
      },
      {
        "item": "SUM_BELOW",
        "inGameDate": "2023/2/27",
        "level": 0,
        "moneyBefore": 34390,
        "moneyAfter": 34590,
        "type": "achievementAward",
        "moneyEarn": 200,
        "timestamp": "2024-01-15 07:24:41"
      },
      {
        "inGameDate": "2023/2/27",
        "year": 2023,
        "match": "dog_give_power_open",
        "moneyBefore": 34590,
        "moneyAfter": 38590,
        "type": "championshipEarn",
        "items": {"TOP_16": {
          "actual": 4000,
          "raw": 5000
        }},
        "timestamp": "2024-01-15 07:44:06"
      },
      {
        "inGameDate": "2023/2/27",
        "moneyBefore": 38590,
        "moneyAfter": 38410,
        "type": "fees",
        "items": [{
          "item": "lifeFee",
          "moneyCost": 180
        }],
        "timestamp": "2024-01-15 07:45:05"
      },
      {
        "inGameDate": "2023/3/2",
        "moneyBefore": 38410,
        "moneyAfter": 37930,
        "type": "fees",
        "items": [{
          "item": "lifeFee",
          "moneyCost": 480
        }],
        "timestamp": "2024-01-15 07:45:13"
      },
      {
        "item": "POT_FAIL_THREE",
        "inGameDate": "2023/3/10",
        "level": 0,
        "moneyBefore": 37930,
        "moneyAfter": 38130,
        "type": "achievementAward",
        "moneyEarn": 200,
        "timestamp": "2024-01-15 07:45:20"
      },
      {
        "item": "SNOOKER_CUMULATE_FOUL_GAIN",
        "inGameDate": "2023/3/10",
        "level": 0,
        "moneyBefore": 38130,
        "moneyAfter": 38330,
        "type": "achievementAward",
        "moneyEarn": 200,
        "timestamp": "2024-01-15 07:45:26"
      },
      {
        "inGameDate": "2023/3/10",
        "moneyBefore": 38330,
        "moneyAfter": 37850,
        "type": "fees",
        "items": [{
          "item": "lifeFee",
          "moneyCost": 480
        }],
        "timestamp": "2024-01-15 07:45:35"
      },
      {
        "item": 16,
        "inGameDate": "2023/3/18",
        "match": "custom_195B277334903CE5+2023+eight_master_tour_beijing",
        "moneyBefore": 37850,
        "moneyAfter": 38050,
        "type": "invitation",
        "moneyEarn": 200,
        "timestamp": "2024-01-15 07:45:35"
      },
      {
        "inGameDate": "2023/3/18",
        "match": "custom_195B277334903CE5+2023+eight_master_tour_beijing",
        "moneyBefore": 38050,
        "moneyAfter": 37050,
        "type": "participation",
        "items": [
          {
            "item": "registry",
            "moneyCost": 200
          },
          {
            "item": "travel",
            "moneyCost": 400
          },
          {
            "item": "hotel",
            "moneyCost": 400
          }
        ],
        "timestamp": "2024-01-15 07:45:35"
      },
      {
        "inGameDate": "2023/3/18",
        "year": 2023,
        "match": "eight_master_tour_beijing",
        "moneyBefore": 37050,
        "moneyAfter": 41050,
        "type": "championshipEarn",
        "items": {"TOP_16": {
          "actual": 4000,
          "raw": 5000
        }},
        "timestamp": "2024-01-15 07:56:06"
      },
      {
        "inGameDate": "2023/3/18",
        "perkUsed": 1,
        "moneyBefore": 41050,
        "moneyCost": 550,
        "moneyAfter": 40500,
        "ability": {"powerControl": [
          80.94849853825914,
          82.51055859672879
        ]},
        "type": "upgrade",
        "timestamp": "2024-01-15 07:56:39"
      },
      {
        "item": "LOST_ALL_MATCHES",
        "inGameDate": "2023/3/18",
        "level": 0,
        "moneyBefore": 40500,
        "moneyAfter": 40700,
        "type": "achievementAward",
        "moneyEarn": 200,
        "timestamp": "2024-01-15 07:56:43"
      },
      {
        "item": "ONE_ROUND_TOUR",
        "inGameDate": "2023/3/18",
        "level": 0,
        "moneyBefore": 40700,
        "moneyAfter": 40900,
        "type": "achievementAward",
        "moneyEarn": 200,
        "timestamp": "2024-01-15 07:56:43"
      },
      {
        "item": "DEFEAT_BY_CHAMPION",
        "inGameDate": "2023/3/18",
        "level": 0,
        "moneyBefore": 40900,
        "moneyAfter": 41100,
        "type": "achievementAward",
        "moneyEarn": 200,
        "timestamp": "2024-01-15 07:56:51"
      },
      {
        "item": "GET_INVITED",
        "inGameDate": "2023/3/18",
        "level": 0,
        "moneyBefore": 41100,
        "moneyAfter": 41300,
        "type": "achievementAward",
        "moneyEarn": 200,
        "timestamp": "2024-01-15 07:56:51"
      },
      {
        "inGameDate": "2023/3/18",
        "moneyBefore": 41300,
        "moneyAfter": 40880,
        "type": "fees",
        "items": [{
          "item": "lifeFee",
          "moneyCost": 420
        }],
        "timestamp": "2024-01-15 17:25:09"
      },
      {
        "inGameDate": "2023/3/25",
        "match": "custom_195B277334903CE5+2023+china_open",
        "moneyBefore": 40880,
        "moneyAfter": 39880,
        "type": "participation",
        "items": [
          {
            "item": "registry",
            "moneyCost": 200
          },
          {
            "item": "travel",
            "moneyCost": 400
          },
          {
            "item": "hotel",
            "moneyCost": 400
          }
        ],
        "timestamp": "2024-01-15 17:25:09"
      },
      {
        "item": "WIN_FRAMES",
        "inGameDate": "2023/3/25",
        "level": 1,
        "moneyBefore": 39880,
        "moneyAfter": 40380,
        "type": "achievementAward",
        "moneyEarn": 500,
        "timestamp": "2024-01-15 17:43:10"
      },
      {
        "itemType": "tip",
        "item": "primeTipSoft:custom_195B277334903CE5-362",
        "inGameDate": "2023/3/25",
        "moneyBefore": 40380,
        "moneyCost": 80,
        "moneyAfter": 40300,
        "type": "purchase",
        "timestamp": "2024-01-15 17:55:14"
      },
      {
        "inGameDate": "2023/3/25",
        "year": 2023,
        "match": "china_open",
        "moneyBefore": 40300,
        "moneyAfter": 42300,
        "type": "championshipEarn",
        "items": {"TOP_32": {
          "actual": 2000,
          "raw": 2500
        }},
        "timestamp": "2024-01-15 18:18:36"
      },
      {
        "inGameDate": "2023/3/25",
        "moneyBefore": 42300,
        "moneyAfter": 42000,
        "type": "fees",
        "items": [{
          "item": "lifeFee",
          "moneyCost": 300
        }],
        "timestamp": "2024-01-15 18:19:18"
      },
      {
        "inGameDate": "2023/3/30",
        "match": "custom_195B277334903CE5+2023+eight_spadina_open",
        "moneyBefore": 42000,
        "moneyAfter": 41000,
        "type": "participation",
        "items": [
          {
            "item": "registry",
            "moneyCost": 200
          },
          {
            "item": "travel",
            "moneyCost": 400
          },
          {
            "item": "hotel",
            "moneyCost": 400
          }
        ],
        "timestamp": "2024-01-15 18:19:18"
      },
      {
        "inGameDate": "2023/3/30",
        "year": 2023,
        "match": "eight_spadina_open",
        "moneyBefore": 41000,
        "moneyAfter": 57000,
        "type": "championshipEarn",
        "items": {"CHAMPION": {
          "actual": 16000,
          "raw": 20000
        }},
        "timestamp": "2024-01-15 18:49:56"
      },
      {
        "inGameDate": "2023/3/30",
        "perkUsed": 7,
        "moneyBefore": 57000,
        "moneyCost": 4550,
        "moneyAfter": 52450,
        "ability": {
          "cuePrecision": [
            80.98076777205624,
            82.54153706117398
          ],
          "normalPower": [
            80.20370542063067,
            81.91253491565323
          ],
          "spin": [
            88.64548414551548,
            91.10367818850706
          ],
          "aiming": [
            77.79804348928985,
            81.10667687972953
          ]
        },
        "type": "upgrade",
        "timestamp": "2024-01-15 18:50:36"
      },
      {
        "item": "PASS_POT",
        "inGameDate": "2023/3/30",
        "level": 0,
        "moneyBefore": 52450,
        "moneyAfter": 52650,
        "type": "achievementAward",
        "moneyEarn": 200,
        "timestamp": "2024-01-15 18:50:48"
      },
      {
        "item": "FINAL_STAGE",
        "inGameDate": "2023/3/30",
        "level": 0,
        "moneyBefore": 52650,
        "moneyAfter": 52850,
        "type": "achievementAward",
        "moneyEarn": 200,
        "timestamp": "2024-01-15 18:50:50"
      },
      {
        "item": "CEB_CUMULATIVE_CLEAR",
        "inGameDate": "2023/3/30",
        "level": 0,
        "moneyBefore": 52850,
        "moneyAfter": 53050,
        "type": "achievementAward",
        "moneyEarn": 200,
        "timestamp": "2024-01-15 18:50:55"
      },
      {
        "item": "BLIND_SHOT",
        "inGameDate": "2023/3/30",
        "level": 0,
        "moneyBefore": 53050,
        "moneyAfter": 53250,
        "type": "achievementAward",
        "moneyEarn": 200,
        "timestamp": "2024-01-15 18:50:56"
      },
      {
        "item": "CHAMPION",
        "inGameDate": "2023/3/30",
        "level": 0,
        "moneyBefore": 53250,
        "moneyAfter": 53450,
        "type": "achievementAward",
        "moneyEarn": 200,
        "timestamp": "2024-01-15 18:50:58"
      },
      {
        "item": "DEFEAT_UNIQUE_OPPONENTS_SNOOKER",
        "inGameDate": "2023/3/30",
        "level": 0,
        "moneyBefore": 53450,
        "moneyAfter": 53650,
        "type": "achievementAward",
        "moneyEarn": 200,
        "timestamp": "2024-01-15 18:51:00"
      },
      {
        "item": "DEFEAT_SAME_OPPONENT_CONTINUOUS_CEB",
        "inGameDate": "2023/3/30",
        "level": 0,
        "moneyBefore": 53650,
        "moneyAfter": 53850,
        "type": "achievementAward",
        "moneyEarn": 200,
        "timestamp": "2024-01-15 18:51:02"
      },
      {
        "item": "DEFEAT_UNIQUE_OPPONENTS_CEB",
        "inGameDate": "2023/3/30",
        "level": 1,
        "moneyBefore": 53850,
        "moneyAfter": 54350,
        "type": "achievementAward",
        "moneyEarn": 500,
        "timestamp": "2024-01-15 18:51:03"
      },
      {
        "item": "CHAMP_EARN_CUMULATIVE",
        "inGameDate": "2023/3/30",
        "level": 0,
        "moneyBefore": 54350,
        "moneyAfter": 54550,
        "type": "achievementAward",
        "moneyEarn": 200,
        "timestamp": "2024-01-15 18:51:04"
      },
      {
        "item": "SAVE_MONEY",
        "inGameDate": "2023/3/30",
        "level": 0,
        "moneyBefore": 54550,
        "moneyAfter": 54750,
        "type": "achievementAward",
        "moneyEarn": 200,
        "timestamp": "2024-01-15 18:51:04"
      },
      {
        "item": "BUY_ITEMS",
        "inGameDate": "2023/3/30",
        "level": 1,
        "moneyBefore": 54750,
        "moneyAfter": 55250,
        "type": "achievementAward",
        "moneyEarn": 500,
        "timestamp": "2024-01-15 18:51:05"
      },
      {
        "inGameDate": "2023/3/30",
        "moneyBefore": 55250,
        "moneyAfter": 54170,
        "type": "fees",
        "items": [{
          "item": "lifeFee",
          "moneyCost": 1080
        }],
        "timestamp": "2024-01-15 19:44:55"
      },
      {
        "inGameDate": "2023/4/17",
        "match": "custom_195B277334903CE5+2023+world_champ",
        "moneyBefore": 54170,
        "moneyAfter": 49970,
        "type": "participation",
        "items": [
          {
            "item": "registry",
            "moneyCost": 200
          },
          {
            "item": "travel",
            "moneyCost": 2000
          },
          {
            "item": "hotel",
            "moneyCost": 2000
          }
        ],
        "timestamp": "2024-01-15 19:44:55"
      },
      {
        "itemType": "cue",
        "item": "profSnookerCueThicker:custom_195B277334903CE5-364",
        "inGameDate": "2023/4/17",
        "moneyBefore": 49970,
        "moneyCost": 1000,
        "moneyAfter": 48970,
        "type": "purchase",
        "timestamp": "2024-01-15 21:10:50"
      },
      {
        "inGameDate": "2023/4/17",
        "year": 2023,
        "match": "world_champ",
        "moneyBefore": 48970,
        "moneyAfter": 64970,
        "type": "championshipEarn",
        "items": {"TOP_32": {
          "actual": 16000,
          "raw": 20000
        }},
        "timestamp": "2024-01-15 21:20:58"
      },
      {
        "inGameDate": "2023/4/17",
        "perkUsed": 13,
        "moneyBefore": 64970,
        "moneyCost": 10250,
        "moneyAfter": 54720,
        "ability": {
          "rest": [
            81.44051382382838,
            83.75408299439869
          ],
          "cuePrecision": [
            82.54153706117398,
            85.47828055557794
          ],
          "normalPower": [
            81.91253491565323,
            84.22789649113537
          ],
          "spin": [
            91.10367818850706,
            95.45700847275552
          ],
          "spinControl": [
            82.59429148739287,
            84.09051982789715
          ],
          "aiming": [
            81.10667687972953,
            84.15591341235873
          ]
        },
        "type": "upgrade",
        "timestamp": "2024-01-15 21:21:48"
      },
      {
        "inGameDate": "2023/4/17",
        "perkUsed": 2,
        "moneyBefore": 54720,
        "moneyCost": 1350,
        "moneyAfter": 53370,
        "ability": {"normalPower": [
          84.22789649113537,
          85.62122940623036
        ]},
        "type": "upgrade",
        "timestamp": "2024-01-15 21:21:57"
      },
      {
        "item": "SNOOKER_CUMULATE_SCORE",
        "inGameDate": "2023/4/17",
        "level": 1,
        "moneyBefore": 53370,
        "moneyAfter": 53870,
        "type": "achievementAward",
        "moneyEarn": 500,
        "timestamp": "2024-01-15 21:25:04"
      },
      {
        "item": "NOT_CONCEDE",
        "inGameDate": "2023/4/17",
        "level": 0,
        "moneyBefore": 53870,
        "moneyAfter": 54070,
        "type": "achievementAward",
        "moneyEarn": 200,
        "timestamp": "2024-01-15 21:25:05"
      },
      {
        "item": "EXPENDITURE",
        "inGameDate": "2023/4/17",
        "level": 1,
        "moneyBefore": 54070,
        "moneyAfter": 54570,
        "type": "achievementAward",
        "moneyEarn": 500,
        "timestamp": "2024-01-15 21:25:11"
      },
      {
        "inGameDate": "2023/4/17",
        "moneyBefore": 54570,
        "moneyAfter": 53730,
        "type": "fees",
        "items": [{
          "item": "lifeFee",
          "moneyCost": 840
        }],
        "timestamp": "2024-01-15 21:25:51"
      },
      {
        "item": 7,
        "inGameDate": "2023/5/1",
        "match": "custom_195B277334903CE5+2023+eight_noob_open",
        "moneyBefore": 53730,
        "moneyAfter": 53930,
        "type": "invitation",
        "moneyEarn": 200,
        "timestamp": "2024-01-15 21:25:52"
      },
      {
        "inGameDate": "2023/5/1",
        "match": "custom_195B277334903CE5+2023+eight_noob_open",
        "moneyBefore": 53930,
        "moneyAfter": 52730,
        "type": "participation",
        "items": [
          {
            "item": "registry",
            "moneyCost": 200
          },
          {
            "item": "travel",
            "moneyCost": 400
          },
          {
            "item": "hotel",
            "moneyCost": 600
          }
        ],
        "timestamp": "2024-01-15 21:25:52"
      },
      {
        "item": "POT_BALLS",
        "inGameDate": "2023/5/1",
        "level": 2,
        "moneyBefore": 52730,
        "moneyAfter": 53730,
        "type": "achievementAward",
        "moneyEarn": 1000,
        "timestamp": "2024-01-15 21:40:16"
      },
      {
        "item": "SNOOKER_TOP_64",
        "inGameDate": "2023/5/1",
        "level": 0,
        "moneyBefore": 53730,
        "moneyAfter": 53930,
        "type": "achievementAward",
        "moneyEarn": 200,
        "timestamp": "2024-01-15 21:40:23"
      },
      {
        "inGameDate": "2023/5/1",
        "year": 2023,
        "match": "eight_noob_open",
        "moneyBefore": 53930,
        "moneyAfter": 55930,
        "type": "championshipEarn",
        "items": {"TOP_32": {
          "actual": 2000,
          "raw": 2500
        }},
        "timestamp": "2024-01-15 21:44:06"
      },
      {
        "item": "PARTICIPATE_TOURNAMENTS",
        "inGameDate": "2023/5/1",
        "level": 1,
        "moneyBefore": 55930,
        "moneyAfter": 56430,
        "type": "achievementAward",
        "moneyEarn": 500,
        "timestamp": "2024-01-15 21:44:25"
      },
      {
        "item": "MAIN_OF_TOURNAMENTS",
        "inGameDate": "2023/5/1",
        "level": 1,
        "moneyBefore": 56430,
        "moneyAfter": 56930,
        "type": "achievementAward",
        "moneyEarn": 500,
        "timestamp": "2024-01-15 21:44:26"
      },
      {
        "inGameDate": "2023/5/1",
        "moneyBefore": 56930,
        "moneyAfter": 55490,
        "type": "fees",
        "items": [{
          "item": "lifeFee",
          "moneyCost": 1440
        }],
        "timestamp": "2024-01-15 21:51:38"
      },
      {
        "inGameDate": "2023/5/25",
        "match": "custom_195B277334903CE5+2023+space_grand_prix",
        "moneyBefore": 55490,
        "moneyAfter": 52290,
        "type": "participation",
        "items": [
          {
            "item": "registry",
            "moneyCost": 500
          },
          {
            "item": "travel",
            "moneyCost": 1800
          },
          {
            "item": "hotel",
            "moneyCost": 900
          }
        ],
        "timestamp": "2024-01-15 21:51:38"
      },
      {
        "itemType": "tip",
        "item": "primeTipMedium:custom_195B277334903CE5-365",
        "inGameDate": "2023/5/25",
        "moneyBefore": 52290,
        "moneyCost": 80,
        "moneyAfter": 52210,
        "type": "purchase",
        "timestamp": "2024-01-15 21:52:17"
      },
      {
        "inGameDate": "2023/5/25",
        "year": 2023,
        "match": "space_grand_prix",
        "moneyBefore": 52210,
        "moneyAfter": 52210,
        "type": "championshipEarn",
        "items": {"PRE_GAMES_1": {
          "actual": 0,
          "raw": 0
        }},
        "timestamp": "2024-01-15 22:03:02"
      },
      {
        "inGameDate": "2023/5/25",
        "moneyBefore": 52210,
        "moneyAfter": 50770,
        "type": "fees",
        "items": [{
          "item": "lifeFee",
          "moneyCost": 1440
        }],
        "timestamp": "2024-01-16 01:24:54"
      },
      {
        "item": 7,
        "inGameDate": "2023/6/18",
        "match": "custom_195B277334903CE5+2023+eight_master_tour_xian",
        "moneyBefore": 50770,
        "moneyAfter": 50970,
        "type": "invitation",
        "moneyEarn": 200,
        "timestamp": "2024-01-16 01:24:54"
      },
      {
        "inGameDate": "2023/6/18",
        "match": "custom_195B277334903CE5+2023+eight_master_tour_xian",
        "moneyBefore": 50970,
        "moneyAfter": 49970,
        "type": "participation",
        "items": [
          {
            "item": "registry",
            "moneyCost": 200
          },
          {
            "item": "travel",
            "moneyCost": 400
          },
          {
            "item": "hotel",
            "moneyCost": 400
          }
        ],
        "timestamp": "2024-01-16 01:24:54"
      },
      {
        "inGameDate": "2023/6/18",
        "year": 2023,
        "match": "eight_master_tour_xian",
        "moneyBefore": 49970,
        "moneyAfter": 57170,
        "type": "championshipEarn",
        "items": {"TOP_8": {
          "actual": 7200,
          "raw": 9000
        }},
        "timestamp": "2024-01-16 02:17:52"
      },
      {
        "inGameDate": "2023/6/18",
        "moneyBefore": 57170,
        "moneyAfter": 56570,
        "type": "fees",
        "items": [{
          "item": "lifeFee",
          "moneyCost": 600
        }],
        "timestamp": "2024-01-16 02:18:15"
      },
      {
        "inGameDate": "2023/6/28",
        "match": "custom_195B277334903CE5+2023+american_nine_sydney_burwood_cup",
        "moneyBefore": 56570,
        "moneyAfter": 55570,
        "type": "participation",
        "items": [
          {
            "item": "registry",
            "moneyCost": 200
          },
          {
            "item": "travel",
            "moneyCost": 400
          },
          {
            "item": "hotel",
            "moneyCost": 400
          }
        ],
        "timestamp": "2024-01-16 02:18:15"
      },
      {
        "inGameDate": "2023/6/28",
        "year": 2023,
        "match": "american_nine_sydney_burwood_cup",
        "moneyBefore": 55570,
        "moneyAfter": 56770,
        "type": "championshipEarn",
        "items": {"TOP_16": {
          "actual": 1200,
          "raw": 1500
        }},
        "timestamp": "2024-01-16 02:32:42"
      },
      {
        "inGameDate": "2023/6/28",
        "perkUsed": 6,
        "moneyBefore": 56770,
        "moneyCost": 5100,
        "moneyAfter": 51670,
        "ability": {
          "rest": [
            83.75408299439869,
            85.92883801473477
          ],
          "cuePrecision": [
            85.47828055557794,
            86.85914933335482
          ],
          "spin": [
            95.45700847275552,
            96.4387281338453
          ],
          "antiHand": [
            50,
            52.8
          ],
          "spinControl": [
            84.09051982789715,
            85.52689903478127
          ],
          "aiming": [
            84.15591341235873,
            85.58967687586438
          ]
        },
        "type": "upgrade",
        "timestamp": "2024-01-16 02:33:01"
      },
      {
        "inGameDate": "2023/6/28",
        "moneyBefore": 51670,
        "moneyAfter": 50950,
        "type": "fees",
        "items": [{
          "item": "lifeFee",
          "moneyCost": 720
        }],
        "timestamp": "2024-01-16 02:35:50"
      },
      {
        "inGameDate": "2023/7/10",
        "match": "custom_195B277334903CE5+2023+chongqing_open",
        "moneyBefore": 50950,
        "moneyAfter": 49950,
        "type": "participation",
        "items": [
          {
            "item": "registry",
            "moneyCost": 200
          },
          {
            "item": "travel",
            "moneyCost": 400
          },
          {
            "item": "hotel",
            "moneyCost": 400
          }
        ],
        "timestamp": "2024-01-16 02:35:50"
      },
      {
        "inGameDate": "2023/7/10",
        "year": 2023,
        "match": "chongqing_open",
        "moneyBefore": 49950,
        "moneyAfter": 54750,
        "type": "championshipEarn",
        "items": {"TOP_8": {
          "actual": 4800,
          "raw": 6000
        }},
        "timestamp": "2024-01-16 23:11:39"
      },
      {
        "inGameDate": "2023/7/10",
        "moneyBefore": 54750,
        "moneyAfter": 54090,
        "type": "fees",
        "items": [{
          "item": "lifeFee",
          "moneyCost": 660
        }],
        "timestamp": "2024-01-16 23:12:07"
      },
      {
        "item": 6,
        "inGameDate": "2023/7/21",
        "match": "custom_195B277334903CE5+2023+eight_duck_goose_open",
        "moneyBefore": 54090,
        "moneyAfter": 54890,
        "type": "invitation",
        "moneyEarn": 800,
        "timestamp": "2024-01-16 23:12:07"
      },
      {
        "inGameDate": "2023/7/21",
        "match": "custom_195B277334903CE5+2023+eight_duck_goose_open",
        "moneyBefore": 54890,
        "moneyAfter": 52390,
        "type": "participation",
        "items": [
          {
            "item": "registry",
            "moneyCost": 200
          },
          {
            "item": "travel",
            "moneyCost": 1800
          },
          {
            "item": "hotel",
            "moneyCost": 500
          }
        ],
        "timestamp": "2024-01-16 23:12:07"
      },
      {
        "inGameDate": "2023/7/21",
        "year": 2023,
        "match": "eight_duck_goose_open",
        "moneyBefore": 52390,
        "moneyAfter": 54390,
        "type": "championshipEarn",
        "items": {"TOP_16": {
          "actual": 2000,
          "raw": 2500
        }},
        "timestamp": "2024-01-16 23:21:20"
      },
      {
        "inGameDate": "2023/7/21",
        "moneyBefore": 54390,
        "moneyAfter": 53490,
        "type": "fees",
        "items": [{
          "item": "lifeFee",
          "moneyCost": 900
        }],
        "timestamp": "2024-01-17 05:45:12"
      },
      {
        "inGameDate": "2023/8/5",
        "match": "custom_195B277334903CE5+2023+american_nine_give_power_open",
        "moneyBefore": 53490,
        "moneyAfter": 50890,
        "type": "participation",
        "items": [
          {
            "item": "registry",
            "moneyCost": 200
          },
          {
            "item": "travel",
            "moneyCost": 1800
          },
          {
            "item": "hotel",
            "moneyCost": 600
          }
        ],
        "timestamp": "2024-01-17 05:45:12"
      },
      {
        "inGameDate": "2023/8/5",
        "year": 2023,
        "match": "american_nine_give_power_open",
        "moneyBefore": 50890,
        "moneyAfter": 52490,
        "type": "championshipEarn",
        "items": {"TOP_64": {
          "actual": 1600,
          "raw": 2000
        }},
        "timestamp": "2024-01-17 05:50:31"
      },
      {
        "inGameDate": "2023/8/5",
        "perkUsed": 3,
        "moneyBefore": 52490,
        "moneyCost": 2750,
        "moneyAfter": 49740,
        "ability": {"rest": [
          85.92883801473477,
          91.70103799363046
        ]},
        "type": "upgrade",
        "timestamp": "2024-01-17 05:50:53"
      },
      {
        "inGameDate": "2023/8/5",
        "moneyBefore": 49740,
        "moneyAfter": 48720,
        "type": "fees",
        "items": [{
          "item": "lifeFee",
          "moneyCost": 1020
        }],
        "timestamp": "2024-01-17 05:51:15"
      },
      {
        "inGameDate": "2023/8/22",
        "match": "custom_195B277334903CE5+2023+eight_master",
        "moneyBefore": 48720,
        "moneyAfter": 47920,
        "type": "participation",
        "items": [
          {
            "item": "registry",
            "moneyCost": 0
          },
          {
            "item": "travel",
            "moneyCost": 400
          },
          {
            "item": "hotel",
            "moneyCost": 400
          }
        ],
        "timestamp": "2024-01-17 05:51:15"
      },
      {
        "inGameDate": "2023/8/22",
        "match": "pool-full-ordered-regular",
        "moneyBefore": 47920,
        "moneyAfter": 47920,
        "type": "challengeEarn",
        "items": {},
        "timestamp": "2024-01-17 06:13:44"
      },
      {
        "item": "MISCUE_POT",
        "inGameDate": "2023/8/22",
        "level": 0,
        "moneyBefore": 47920,
        "moneyAfter": 48120,
        "type": "achievementAward",
        "moneyEarn": 200,
        "timestamp": "2024-01-17 06:13:49"
      },
      {
        "item": "DOUBLE_POT_WIN",
        "inGameDate": "2023/8/22",
        "level": 0,
        "moneyBefore": 48120,
        "moneyAfter": 48320,
        "type": "achievementAward",
        "moneyEarn": 200,
        "timestamp": "2024-01-17 06:14:01"
      },
      {
        "item": "POT_OPPONENT_BALL",
        "inGameDate": "2023/8/22",
        "level": 0,
        "moneyBefore": 48320,
        "moneyAfter": 48520,
        "type": "achievementAward",
        "moneyEarn": 200,
        "timestamp": "2024-01-17 06:14:03"
      },
      {
        "item": "PASS_NINE",
        "inGameDate": "2023/8/22",
        "level": 0,
        "moneyBefore": 48520,
        "moneyAfter": 48720,
        "type": "achievementAward",
        "moneyEarn": 200,
        "timestamp": "2024-01-17 06:14:05"
      },
      {
        "item": "DEFEAT_UNIQUE_OPPONENTS_SNOOKER",
        "inGameDate": "2023/8/22",
        "level": 1,
        "moneyBefore": 48720,
        "moneyAfter": 49220,
        "type": "achievementAward",
        "moneyEarn": 500,
        "timestamp": "2024-01-17 06:14:08"
      },
      {
        "item": "POT_BALLS_ANTI",
        "inGameDate": "2023/8/22",
        "level": 0,
        "moneyBefore": 49220,
        "moneyAfter": 49420,
        "type": "achievementAward",
        "moneyEarn": 200,
        "timestamp": "2024-01-17 06:14:18"
      },
      {
        "inGameDate": "2023/8/22",
        "year": 2023,
        "match": "eight_master",
        "moneyBefore": 49420,
        "moneyAfter": 145420,
        "type": "championshipEarn",
        "items": {"SECOND_PLACE": {
          "actual": 96000,
          "raw": 120000
        }},
        "timestamp": "2024-01-17 22:26:11"
      },
      {
        "inGameDate": "2023/8/22",
        "perkUsed": 8,
        "moneyBefore": 145420,
        "moneyCost": 5700,
        "moneyAfter": 139720,
        "ability": {
          "cuePrecision": [
            86.85914933335482,
            88.18478336002063
          ],
          "normalPower": [
            85.62122940623036,
            86.42038022998113
          ],
          "spin": [
            96.4387281338453,
            97.38117900849149
          ],
          "antiHand": [
            52.8,
            60.545740800000004
          ],
          "spinControl": [
            85.52689903478127,
            86.90582307339001
          ],
          "aiming": [
            85.58967687586438,
            86.9660898008298
          ]
        },
        "type": "upgrade",
        "timestamp": "2024-01-17 22:26:53"
      },
      {
        "item": "PASS_POT",
        "inGameDate": "2023/8/22",
        "level": 1,
        "moneyBefore": 139720,
        "moneyAfter": 140220,
        "type": "achievementAward",
        "moneyEarn": 500,
        "timestamp": "2024-01-17 22:27:06"
      },
      {
        "item": "CEB_CUMULATIVE_CLEAR",
        "inGameDate": "2023/8/22",
        "level": 1,
        "moneyBefore": 140220,
        "moneyAfter": 140720,
        "type": "achievementAward",
        "moneyEarn": 500,
        "timestamp": "2024-01-17 22:27:11"
      },
      {
        "item": "SECOND_PLACE",
        "inGameDate": "2023/8/22",
        "level": 0,
        "moneyBefore": 140720,
        "moneyAfter": 140920,
        "type": "achievementAward",
        "moneyEarn": 200,
        "timestamp": "2024-01-17 22:27:14"
      },
      {
        "item": "CHAMP_EARN_CUMULATIVE",
        "inGameDate": "2023/8/22",
        "level": 1,
        "moneyBefore": 140920,
        "moneyAfter": 141420,
        "type": "achievementAward",
        "moneyEarn": 500,
        "timestamp": "2024-01-17 22:27:17"
      },
      {
        "item": "SAVE_MONEY",
        "inGameDate": "2023/8/22",
        "level": 1,
        "moneyBefore": 141420,
        "moneyAfter": 141920,
        "type": "achievementAward",
        "moneyEarn": 500,
        "timestamp": "2024-01-17 22:27:18"
      },
      {
        "item": "SAVE_MONEY",
        "inGameDate": "2023/8/22",
        "level": 2,
        "moneyBefore": 141920,
        "moneyAfter": 142920,
        "type": "achievementAward",
        "moneyEarn": 1000,
        "timestamp": "2024-01-17 22:27:19"
      },
      {
        "itemType": "cue",
        "item": "carbonSnookerCue:custom_195B277334903CE5-367",
        "inGameDate": "2023/8/22",
        "moneyBefore": 142920,
        "moneyCost": 2500,
        "moneyAfter": 140420,
        "type": "purchase",
        "timestamp": "2024-01-17 23:33:55"
      },
      {
        "inGameDate": "2023/8/22",
        "moneyBefore": 140420,
        "moneyAfter": 138040,
        "type": "fees",
        "items": [{
          "item": "lifeFee",
          "moneyCost": 2380
        }],
        "timestamp": "2024-01-17 23:41:03"
      },
      {
        "inGameDate": "2023/9/25",
        "match": "custom_195B277334903CE5+2023+challenger_open",
        "moneyBefore": 138040,
        "moneyAfter": 134040,
        "type": "participation",
        "items": [
          {
            "item": "registry",
            "moneyCost": 1000
          },
          {
            "item": "travel",
            "moneyCost": 2000
          },
          {
            "item": "hotel",
            "moneyCost": 1000
          }
        ],
        "timestamp": "2024-01-17 23:41:03"
      },
      {
        "itemType": "tip",
        "item": "primeTipMedium:custom_195B277334903CE5-368",
        "inGameDate": "2023/9/25",
        "moneyBefore": 134040,
        "moneyCost": 80,
        "moneyAfter": 133960,
        "type": "purchase",
        "timestamp": "2024-01-17 23:41:15"
      },
      {
        "inGameDate": "2023/9/25",
        "year": 2023,
        "match": "challenger_open",
        "moneyBefore": 133960,
        "moneyAfter": 133960,
        "type": "championshipEarn",
        "items": {"PRE_GAMES_3": {
          "actual": 0,
          "raw": 0
        }},
        "timestamp": "2024-01-18 02:11:21"
      },
      {
        "inGameDate": "2023/9/25",
        "perkUsed": 5,
        "moneyBefore": 133960,
        "moneyCost": 3000,
        "moneyAfter": 130960,
        "ability": {
          "cuePrecision": [
            88.18478336002063,
            89.45739202561981
          ],
          "antiHand": [
            60.545740800000004,
            65.20695472128
          ],
          "aiming": [
            86.9660898008298,
            89.55594836044475
          ]
        },
        "type": "upgrade",
        "timestamp": "2024-01-18 02:11:55"
      },
      {
        "inGameDate": "2023/9/25",
        "moneyBefore": 130960,
        "moneyAfter": 129420,
        "type": "fees",
        "items": [{
          "item": "lifeFee",
          "moneyCost": 1540
        }],
        "timestamp": "2024-01-18 02:20:50"
      },
      {
        "item": 6,
        "inGameDate": "2023/10/18",
        "match": "custom_195B277334903CE5+2023+eight_master_tour_hebei",
        "moneyBefore": 129420,
        "moneyAfter": 129620,
        "type": "invitation",
        "moneyEarn": 200,
        "timestamp": "2024-01-18 02:20:50"
      },
      {
        "inGameDate": "2023/10/18",
        "match": "custom_195B277334903CE5+2023+eight_master_tour_hebei",
        "moneyBefore": 129620,
        "moneyAfter": 128620,
        "type": "participation",
        "items": [
          {
            "item": "registry",
            "moneyCost": 200
          },
          {
            "item": "travel",
            "moneyCost": 400
          },
          {
            "item": "hotel",
            "moneyCost": 400
          }
        ],
        "timestamp": "2024-01-18 02:20:50"
      },
      {
        "inGameDate": "2023/10/18",
        "year": 2023,
        "match": "eight_master_tour_hebei",
        "moneyBefore": 128620,
        "moneyAfter": 192620,
        "type": "championshipEarn",
        "items": {"CHAMPION": {
          "actual": 64000,
          "raw": 80000
        }},
        "timestamp": "2024-01-19 02:03:09"
      },
      {
        "inGameDate": "2023/10/18",
        "perkUsed": 2,
        "moneyBefore": 192620,
        "moneyCost": 600,
        "moneyAfter": 192020,
        "ability": {"antiHand": [
          65.20695472128,
          69.50272947113164
        ]},
        "type": "upgrade",
        "timestamp": "2024-01-19 02:03:25"
      },
      {
        "inGameDate": "2023/10/18",
        "moneyBefore": 192020,
        "moneyAfter": 191140,
        "type": "fees",
        "items": [{
          "item": "lifeFee",
          "moneyCost": 880
        }],
        "timestamp": "2024-01-19 02:03:33"
      },
      {
        "inGameDate": "2023/10/29",
        "moneyBefore": 191140,
        "moneyAfter": 190020,
        "type": "fees",
        "items": [{
          "item": "lifeFee",
          "moneyCost": 1120
        }],
        "timestamp": "2024-01-19 02:04:16"
      },
      {
        "inGameDate": "2023/11/12",
        "match": "custom_195B277334903CE5+2023+united_kingdom_champ",
        "moneyBefore": 190020,
        "moneyAfter": 186820,
        "type": "participation",
        "items": [
          {
            "item": "registry",
            "moneyCost": 200
          },
          {
            "item": "travel",
            "moneyCost": 2000
          },
          {
            "item": "hotel",
            "moneyCost": 1000
          }
        ],
        "timestamp": "2024-01-19 02:04:16"
      },
      {
        "item": "BIG_HEART",
        "inGameDate": "2023/11/12",
        "level": 0,
        "moneyBefore": 186820,
        "moneyAfter": 187020,
        "type": "achievementAward",
        "moneyEarn": 200,
        "timestamp": "2024-01-19 02:23:13"
      },
      {
        "item": "POT_TWO_LEGAL",
        "inGameDate": "2023/11/12",
        "level": 0,
        "moneyBefore": 187020,
        "moneyAfter": 187220,
        "type": "achievementAward",
        "moneyEarn": 200,
        "timestamp": "2024-01-19 02:23:17"
      },
      {
        "item": "FINAL_FRAME_USUAL_GUEST",
        "inGameDate": "2023/11/12",
        "level": 0,
        "moneyBefore": 187220,
        "moneyAfter": 187420,
        "type": "achievementAward",
        "moneyEarn": 200,
        "timestamp": "2024-01-19 02:23:19"
      },
      {
        "item": "DEFEAT_SAME_OPPONENT_MULTI_CEB_1",
        "inGameDate": "2023/11/12",
        "level": 0,
        "moneyBefore": 187420,
        "moneyAfter": 187620,
        "type": "achievementAward",
        "moneyEarn": 200,
        "timestamp": "2024-01-19 02:23:40"
      },
      {
        "item": "POT_BALLS_REST",
        "inGameDate": "2023/11/12",
        "level": 2,
        "moneyBefore": 187620,
        "moneyAfter": 188620,
        "type": "achievementAward",
        "moneyEarn": 1000,
        "timestamp": "2024-01-19 02:24:07"
      },
      {
        "item": "CUMULATIVE_LONG_POTS_1",
        "inGameDate": "2023/11/12",
        "level": 2,
        "moneyBefore": 188620,
        "moneyAfter": 189620,
        "type": "achievementAward",
        "moneyEarn": 1000,
        "timestamp": "2024-01-19 02:24:09"
      },
      {
        "itemType": "tip",
        "item": "primeTipMedium:custom_195B277334903CE5-369",
        "inGameDate": "2023/11/12",
        "moneyBefore": 189620,
        "moneyCost": 80,
        "moneyAfter": 189540,
        "type": "purchase",
        "timestamp": "2024-01-20 06:14:25"
      },
      {
        "inGameDate": "2023/11/12",
        "year": 2023,
        "match": "united_kingdom_champ",
        "moneyBefore": 189540,
        "moneyAfter": 201540,
        "type": "championshipEarn",
        "items": {"TOP_16": {
          "actual": 12000,
          "raw": 15000
        }},
        "timestamp": "2024-01-20 18:18:53"
      },
      {
        "inGameDate": "2023/11/12",
        "perkUsed": 10,
        "moneyBefore": 201540,
        "moneyCost": 10350,
        "moneyAfter": 191190,
        "ability": {
          "rest": [
            91.70103799363046,
            93.39897571401264
          ],
          "cuePrecision": [
            89.45739202561981,
            92.97785519117878
          ],
          "spin": [
            97.38117900849149,
            98.28593184815183
          ],
          "antiHand": [
            69.50272947113164,
            73.46171548059492
          ],
          "aiming": [
            89.55594836044475,
            93.06505152862644
          ]
        },
        "type": "upgrade",
        "timestamp": "2024-01-20 18:19:32"
      },
      {
        "inGameDate": "2023/11/12",
        "perkUsed": 2,
        "moneyBefore": 191190,
        "moneyCost": 2000,
        "moneyAfter": 189190,
        "ability": {
          "spin": [
            98.28593184815183,
            99.15449457422577
          ],
          "antiHand": [
            73.46171548059492,
            75.32324686137112
          ]
        },
        "type": "upgrade",
        "timestamp": "2024-01-20 18:19:42"
      },
      {
        "inGameDate": "2023/11/12",
        "moneyBefore": 189190,
        "moneyAfter": 186950,
        "type": "fees",
        "items": [{
          "item": "lifeFee",
          "moneyCost": 2240
        }],
        "timestamp": "2024-01-20 18:20:35"
      },
      {
        "inGameDate": "2023/12/10",
        "moneyBefore": 186950,
        "moneyAfter": 184070,
        "type": "fees",
        "items": [{
          "item": "lifeFee",
          "moneyCost": 2880
        }],
        "timestamp": "2024-01-20 18:20:38"
      },
      {
        "inGameDate": "2024/1/15",
        "moneyBefore": 184070,
        "moneyAfter": 183510,
        "type": "fees",
        "items": [{
          "item": "lifeFee",
          "moneyCost": 560
        }],
        "timestamp": "2024-01-20 18:20:52"
      },
      {
        "inGameDate": "2024/1/22",
        "match": "custom_195B277334903CE5+2024+eight_red_pocket_open",
        "moneyBefore": 183510,
        "moneyAfter": 182510,
        "type": "participation",
        "items": [
          {
            "item": "registry",
            "moneyCost": 200
          },
          {
            "item": "travel",
            "moneyCost": 400
          },
          {
            "item": "hotel",
            "moneyCost": 400
          }
        ],
        "timestamp": "2024-01-20 18:20:52"
      },
      {
        "inGameDate": "2024/1/22",
        "year": 2024,
        "match": "eight_red_pocket_open",
        "moneyBefore": 182510,
        "moneyAfter": 184910,
        "type": "championshipEarn",
        "items": {"TOP_8": {
          "actual": 2400,
          "raw": 3000
        }},
        "timestamp": "2024-01-21 20:52:20"
      },
      {
        "inGameDate": "2024/1/22",
        "moneyBefore": 184910,
        "moneyAfter": 184670,
        "type": "fees",
        "items": [{
          "item": "lifeFee",
          "moneyCost": 240
        }],
        "timestamp": "2024-01-21 20:52:29"
      },
      {
        "inGameDate": "2024/1/25",
        "match": "custom_195B277334903CE5+2024+fresh_hand_open",
        "moneyBefore": 184670,
        "moneyAfter": 181970,
        "type": "participation",
        "items": [
          {
            "item": "registry",
            "moneyCost": 200
          },
          {
            "item": "travel",
            "moneyCost": 2000
          },
          {
            "item": "hotel",
            "moneyCost": 500
          }
        ],
        "timestamp": "2024-01-21 20:52:29"
      },
      {
        "inGameDate": "2024/1/25",
        "year": 2024,
        "match": "fresh_hand_open",
        "moneyBefore": 181970,
        "moneyAfter": 186770,
        "type": "championshipEarn",
        "items": {"TOP_8": {
          "actual": 4800,
          "raw": 6000
        }},
        "timestamp": "2024-01-22 06:27:52"
      },
      {
        "inGameDate": "2024/1/25",
        "moneyBefore": 186770,
        "moneyAfter": 186210,
        "type": "fees",
        "items": [{
          "item": "lifeFee",
          "moneyCost": 560
        }],
        "timestamp": "2024-01-22 06:28:09"
      },
      {
        "inGameDate": "2024/2/1",
        "match": "custom_195B277334903CE5+2024+eight_yangjiaping_mid_cup",
        "moneyBefore": 186210,
        "moneyAfter": 185910,
        "type": "participation",
        "items": [
          {
            "item": "registry",
            "moneyCost": 100
          },
          {
            "item": "travel",
            "moneyCost": 200
          },
          {
            "item": "hotel",
            "moneyCost": 0
          }
        ],
        "timestamp": "2024-01-22 06:28:09"
      },
      {
        "inGameDate": "2024/2/1",
        "year": 2024,
        "match": "eight_yangjiaping_mid_cup",
        "moneyBefore": 185910,
        "moneyAfter": 185910,
        "type": "championshipEarn",
        "items": {"PRE_GAMES_1": {
          "actual": 0,
          "raw": 0
        }},
        "timestamp": "2024-01-22 06:31:33"
      },
      {
        "inGameDate": "2024/2/1",
        "moneyBefore": 185910,
        "moneyAfter": 185190,
        "type": "fees",
        "items": [{
          "item": "lifeFee",
          "moneyCost": 720
        }],
        "timestamp": "2024-01-22 06:31:44"
      },
      {
        "item": 7,
        "inGameDate": "2024/2/10",
        "match": "custom_195B277334903CE5+2024+eight_northeast_open",
        "moneyBefore": 185190,
        "moneyAfter": 185390,
        "type": "invitation",
        "moneyEarn": 200,
        "timestamp": "2024-01-22 06:31:44"
      },
      {
        "inGameDate": "2024/2/10",
        "match": "custom_195B277334903CE5+2024+eight_northeast_open",
        "moneyBefore": 185390,
        "moneyAfter": 184390,
        "type": "participation",
        "items": [
          {
            "item": "registry",
            "moneyCost": 200
          },
          {
            "item": "travel",
            "moneyCost": 400
          },
          {
            "item": "hotel",
            "moneyCost": 400
          }
        ],
        "timestamp": "2024-01-22 06:31:44"
      },
      {
        "itemType": "tip",
        "item": "primeTipMedium:custom_195B277334903CE5-370",
        "inGameDate": "2024/2/10",
        "moneyBefore": 184390,
        "moneyCost": 80,
        "moneyAfter": 184310,
        "type": "purchase",
        "timestamp": "2024-01-22 07:24:23"
      },
      {
        "inGameDate": "2024/2/10",
        "year": 2024,
        "match": "eight_northeast_open",
        "moneyBefore": 184310,
        "moneyAfter": 204310,
        "type": "championshipEarn",
        "items": {"TOP_4": {
          "actual": 20000,
          "raw": 25000
        }},
        "timestamp": "2024-01-22 07:27:35"
      },
      {
        "inGameDate": "2024/2/10",
        "perkUsed": 4,
        "moneyBefore": 204310,
        "moneyCost": 5500,
        "moneyAfter": 198810,
        "ability": {
          "cuePrecision": [
            92.97785519117878,
            95.09639134419035
          ],
          "aiming": [
            93.06505152862644,
            95.17675148878213
          ]
        },
        "type": "upgrade",
        "timestamp": "2024-01-22 07:27:54"
      },
      {
        "inGameDate": "2024/2/10",
        "moneyBefore": 198810,
        "moneyAfter": 197850,
        "type": "fees",
        "items": [{
          "item": "lifeFee",
          "moneyCost": 960
        }],
        "timestamp": "2024-01-22 07:28:40"
      },
      {
        "inGameDate": "2024/2/22",
        "moneyBefore": 197850,
        "moneyAfter": 197450,
        "type": "fees",
        "items": [{
          "item": "lifeFee",
          "moneyCost": 400
        }],
        "timestamp": "2024-01-22 07:29:04"
      },
      {
        "inGameDate": "2024/2/27",
        "match": "custom_195B277334903CE5+2024+dog_give_power_open",
        "moneyBefore": 197450,
        "moneyAfter": 194550,
        "type": "participation",
        "items": [
          {
            "item": "registry",
            "moneyCost": 500
          },
          {
            "item": "travel",
            "moneyCost": 1600
          },
          {
            "item": "hotel",
            "moneyCost": 800
          }
        ],
        "timestamp": "2024-01-22 07:29:04"
      },
      {
        "inGameDate": "2024/2/27",
        "year": 2024,
        "match": "dog_give_power_open",
        "moneyBefore": 194550,
        "moneyAfter": 198550,
        "type": "championshipEarn",
        "items": {"TOP_16": {
          "actual": 4000,
          "raw": 5000
        }},
        "timestamp": "2024-02-03 23:17:54"
      },
      {
        "inGameDate": "2024/2/27",
        "moneyBefore": 198550,
        "moneyAfter": 198230,
        "type": "fees",
        "items": [{
          "item": "lifeFee",
          "moneyCost": 320
        }],
        "timestamp": "2024-02-03 23:18:24"
      },
      {
        "inGameDate": "2024/3/2",
        "moneyBefore": 198230,
        "moneyAfter": 197590,
        "type": "fees",
        "items": [{
          "item": "lifeFee",
          "moneyCost": 640
        }],
        "timestamp": "2024-02-03 23:18:32"
      },
      {
        "inGameDate": "2024/3/10",
        "moneyBefore": 197590,
        "moneyAfter": 196950,
        "type": "fees",
        "items": [{
          "item": "lifeFee",
          "moneyCost": 640
        }],
        "timestamp": "2024-02-03 23:18:34"
      },
      {
        "inGameDate": "2024/3/18",
        "moneyBefore": 196950,
        "moneyAfter": 196390,
        "type": "fees",
        "items": [{
          "item": "lifeFee",
          "moneyCost": 560
        }],
        "timestamp": "2024-02-03 23:18:35"
      },
      {
        "inGameDate": "2024/3/25",
        "match": "custom_195B277334903CE5+2024+china_open",
        "moneyBefore": 196390,
        "moneyAfter": 195390,
        "type": "participation",
        "items": [
          {
            "item": "registry",
            "moneyCost": 200
          },
          {
            "item": "travel",
            "moneyCost": 400
          },
          {
            "item": "hotel",
            "moneyCost": 400
          }
        ],
        "timestamp": "2024-02-03 23:18:35"
      },
      {
        "itemType": "tip",
        "item": "primeTipMedium:custom_195B277334903CE5-371",
        "inGameDate": "2024/3/25",
        "moneyBefore": 195390,
        "moneyCost": 80,
        "moneyAfter": 195310,
        "type": "purchase",
        "timestamp": "2024-02-04 04:09:30"
      },
      {
        "inGameDate": "2024/3/25",
        "year": 2024,
        "match": "china_open",
        "moneyBefore": 195310,
        "moneyAfter": 203310,
        "type": "championshipEarn",
        "items": {"TOP_8": {
          "actual": 8000,
          "raw": 10000
        }},
        "timestamp": "2024-02-05 07:00:55"
      },
      {
        "inGameDate": "2024/3/25",
        "moneyBefore": 203310,
        "moneyAfter": 202910,
        "type": "fees",
        "items": [{
          "item": "lifeFee",
          "moneyCost": 400
        }],
        "timestamp": "2024-02-05 07:01:29"
      },
      {
        "inGameDate": "2024/3/30",
        "match": "custom_195B277334903CE5+2024+eight_spadina_open",
        "moneyBefore": 202910,
        "moneyAfter": 201910,
        "type": "participation",
        "items": [
          {
            "item": "registry",
            "moneyCost": 200
          },
          {
            "item": "travel",
            "moneyCost": 400
          },
          {
            "item": "hotel",
            "moneyCost": 400
          }
        ],
        "timestamp": "2024-02-05 07:01:29"
      },
      {
        "inGameDate": "2024/3/30",
        "year": 2024,
        "match": "eight_spadina_open",
        "moneyBefore": 201910,
        "moneyAfter": 201910,
        "type": "championshipEarn",
        "items": {"PRE_GAMES_1": {
          "actual": 0,
          "raw": 0
        }},
        "timestamp": "2024-02-05 07:05:22"
      },
      {
        "inGameDate": "2024/3/30",
        "moneyBefore": 201910,
        "moneyAfter": 200470,
        "type": "fees",
        "items": [{
          "item": "lifeFee",
          "moneyCost": 1440
        }],
        "timestamp": "2024-02-05 07:05:26"
      },
      {
        "inGameDate": "2024/4/17",
        "match": "custom_195B277334903CE5+2024+world_champ",
        "moneyBefore": 200470,
        "moneyAfter": 196270,
        "type": "participation",
        "items": [
          {
            "item": "registry",
            "moneyCost": 200
          },
          {
            "item": "travel",
            "moneyCost": 2000
          },
          {
            "item": "hotel",
            "moneyCost": 2000
          }
        ],
        "timestamp": "2024-02-05 07:05:26"
      },
      {
        "inGameDate": "2024/4/17",
        "match": "chinese-eight-full-regular",
        "moneyBefore": 196270,
        "moneyAfter": 196270,
        "type": "challengeEarn",
        "items": {"clearance": {
          "actual": 0,
          "raw": 0
        }},
        "timestamp": "2024-02-05 07:42:31"
      },
      {
        "inGameDate": "2024/4/17",
        "perkUsed": 5,
        "moneyBefore": 196270,
        "moneyCost": 5950,
        "moneyAfter": 190320,
        "ability": {
          "cuePrecision": [
            95.09639134419035,
            96.09253569042274
          ],
          "spinControl": [
            86.90582307339001,
            90.72039028265878
          ],
          "aiming": [
            95.17675148878213,
            96.16968142923085
          ]
        },
        "type": "upgrade",
        "timestamp": "2024-02-05 07:42:59"
      },
      {
        "inGameDate": "2024/4/17",
        "match": "snooker-hendry-tough-table-challenge",
        "moneyBefore": 190320,
        "moneyAfter": 191520,
        "type": "challengeEarn",
        "items": {
          ">=,score,70": {
            "actual": 800,
            "raw": 1000
          },
          ">=,score,50": {
            "actual": 400,
            "raw": 500
          }
        },
        "timestamp": "2024-02-05 07:47:24"
      },
      {
        "inGameDate": "2024/4/17",
        "match": "snooker-snake-cross-regular",
        "moneyBefore": 191520,
        "moneyAfter": 191520,
        "type": "challengeEarn",
        "items": {},
        "timestamp": "2024-02-05 07:54:25"
      },
      {
        "inGameDate": "2024/4/17",
        "year": 2024,
        "match": "world_champ",
        "moneyBefore": 191520,
        "moneyAfter": 207520,
        "type": "championshipEarn",
        "items": {"TOP_32": {
          "actual": 16000,
          "raw": 20000
        }},
        "timestamp": "2024-02-07 07:19:55"
      },
      {
        "inGameDate": "2024/4/17",
        "perkUsed": 6,
        "moneyBefore": 207520,
        "moneyCost": 7950,
        "moneyAfter": 199570,
        "ability": {
          "cuePrecision": [
            96.09253569042274,
            97.96688089229359
          ],
          "antiHand": [
            75.32324686137112,
            77.11031698691627
          ],
          "spinControl": [
            90.72039028265878,
            91.89157467135243
          ],
          "aiming": [
            96.16968142923085,
            98.03797840517916
          ]
        },
        "type": "upgrade",
        "timestamp": "2024-02-07 07:20:47"
      },
      {
        "inGameDate": "2024/4/17",
        "moneyBefore": 199570,
        "moneyAfter": 198450,
        "type": "fees",
        "items": [{
          "item": "lifeFee",
          "moneyCost": 1120
        }],
        "timestamp": "2024-02-07 07:22:41"
      },
      {
        "item": 8,
        "inGameDate": "2024/5/1",
        "match": "custom_195B277334903CE5+2024+eight_noob_open",
        "moneyBefore": 198450,
        "moneyAfter": 198650,
        "type": "invitation",
        "moneyEarn": 200,
        "timestamp": "2024-02-07 07:22:41"
      },
      {
        "inGameDate": "2024/5/1",
        "match": "custom_195B277334903CE5+2024+eight_noob_open",
        "moneyBefore": 198650,
        "moneyAfter": 197450,
        "type": "participation",
        "items": [
          {
            "item": "registry",
            "moneyCost": 200
          },
          {
            "item": "travel",
            "moneyCost": 400
          },
          {
            "item": "hotel",
            "moneyCost": 600
          }
        ],
        "timestamp": "2024-02-07 07:22:41"
      },
      {
        "inGameDate": "2024/5/1",
        "perkUsed": 2,
        "moneyBefore": 197450,
        "moneyCost": 950,
        "moneyAfter": 196500,
        "ability": {"antiHand": [
          77.11031698691627,
          80.47286813514205
        ]},
        "type": "upgrade",
        "timestamp": "2024-02-09 05:20:26"
      },
      {
        "item": "LIE_DOWN_WIN",
        "inGameDate": "2024/5/1",
        "level": 0,
        "moneyBefore": 196500,
        "moneyAfter": 196700,
        "type": "achievementAward",
        "moneyEarn": 200,
        "timestamp": "2024-02-09 05:20:30"
      },
      {
        "item": "POT_BALLS_ANTI",
        "inGameDate": "2024/5/1",
        "level": 1,
        "moneyBefore": 196700,
        "moneyAfter": 197200,
        "type": "achievementAward",
        "moneyEarn": 500,
        "timestamp": "2024-02-09 05:20:36"
      },
      {
        "item": "ACCURACY_WIN_LONG",
        "inGameDate": "2024/5/1",
        "level": 0,
        "moneyBefore": 197200,
        "moneyAfter": 197400,
        "type": "achievementAward",
        "moneyEarn": 200,
        "timestamp": "2024-02-09 05:20:38"
      },
      {
        "item": "CONTINUOUS_LONG_POT",
        "inGameDate": "2024/5/1",
        "level": 0,
        "moneyBefore": 197400,
        "moneyAfter": 197600,
        "type": "achievementAward",
        "moneyEarn": 200,
        "timestamp": "2024-02-09 05:20:39"
      },
      {
        "item": "DOUBLE_POT",
        "inGameDate": "2024/5/1",
        "level": 1,
        "moneyBefore": 197600,
        "moneyAfter": 198100,
        "type": "achievementAward",
        "moneyEarn": 500,
        "timestamp": "2024-02-09 05:20:40"
      },
      {
        "item": "WIN_FRAMES",
        "inGameDate": "2024/5/1",
        "level": 2,
        "moneyBefore": 198100,
        "moneyAfter": 199100,
        "type": "achievementAward",
        "moneyEarn": 1000,
        "timestamp": "2024-02-09 05:20:42"
      },
      {
        "item": "WIN_MATCHES",
        "inGameDate": "2024/5/1",
        "level": 2,
        "moneyBefore": 199100,
        "moneyAfter": 200100,
        "type": "achievementAward",
        "moneyEarn": 1000,
        "timestamp": "2024-02-09 05:20:43"
      },
      {
        "item": "SNOOKER_BREAK_100",
        "inGameDate": "2024/5/1",
        "level": 0,
        "moneyBefore": 200100,
        "moneyAfter": 200300,
        "type": "achievementAward",
        "moneyEarn": 200,
        "timestamp": "2024-02-09 05:20:45"
      },
      {
        "item": "SNOOKER_CUMULATE_FOUL_GAIN",
        "inGameDate": "2024/5/1",
        "level": 1,
        "moneyBefore": 200300,
        "moneyAfter": 200800,
        "type": "achievementAward",
        "moneyEarn": 500,
        "timestamp": "2024-02-09 05:20:45"
      },
      {
        "item": "POT_WRONG_COLOR",
        "inGameDate": "2024/5/1",
        "level": 0,
        "moneyBefore": 200800,
        "moneyAfter": 201000,
        "type": "achievementAward",
        "moneyEarn": 200,
        "timestamp": "2024-02-09 05:20:50"
      },
      {
        "item": "CEB_CUMULATIVE_CLEAR",
        "inGameDate": "2024/5/1",
        "level": 2,
        "moneyBefore": 201000,
        "moneyAfter": 202000,
        "type": "achievementAward",
        "moneyEarn": 1000,
        "timestamp": "2024-02-09 05:20:54"
      },
      {
        "item": "PLAY_ONE_YEAR",
        "inGameDate": "2024/5/1",
        "level": 0,
        "moneyBefore": 202000,
        "moneyAfter": 202200,
        "type": "achievementAward",
        "moneyEarn": 200,
        "timestamp": "2024-02-09 05:20:57"
      },
      {
        "item": "DEFEAT_SAME_OPPONENT_CONTINUOUS_SNOOKER",
        "inGameDate": "2024/5/1",
        "level": 0,
        "moneyBefore": 202200,
        "moneyAfter": 202400,
        "type": "achievementAward",
        "moneyEarn": 200,
        "timestamp": "2024-02-09 05:20:59"
      },
      {
        "item": "DEFEAT_SAME_OPPONENT_MULTI_SNOOKER_1",
        "inGameDate": "2024/5/1",
        "level": 0,
        "moneyBefore": 202400,
        "moneyAfter": 202600,
        "type": "achievementAward",
        "moneyEarn": 200,
        "timestamp": "2024-02-09 05:20:59"
      },
      {
        "inGameDate": "2024/5/1",
        "year": 2024,
        "match": "eight_noob_open",
        "moneyBefore": 202600,
        "moneyAfter": 209000,
        "type": "championshipEarn",
        "items": {"TOP_8": {
          "actual": 6400,
          "raw": 8000
        }},
        "timestamp": "2024-02-09 05:37:10"
      },
      {
        "inGameDate": "2024/5/1",
        "perkUsed": 5,
        "moneyBefore": 209000,
        "moneyCost": 4200,
        "moneyAfter": 204800,
        "ability": {
          "rest": [
            93.39897571401264,
            94.99503717117187
          ],
          "powerControl": [
            82.51055859672879,
            84.01013625285964
          ],
          "normalPower": [
            86.42038022998113,
            87.18756502078189
          ],
          "antiHand": [
            80.47286813514205,
            82.05395340973637
          ],
          "spinControl": [
            91.89157467135243,
            93.01591168449833
          ]
        },
        "type": "upgrade",
        "timestamp": "2024-02-09 05:37:29"
      },
      {
        "inGameDate": "2024/5/1",
        "moneyBefore": 204800,
        "moneyAfter": 202880,
        "type": "fees",
        "items": [{
          "item": "lifeFee",
          "moneyCost": 1920
        }],
        "timestamp": "2024-02-09 05:37:36"
      },
      {
        "inGameDate": "2024/5/25",
        "match": "custom_195B277334903CE5+2024+space_grand_prix",
        "moneyBefore": 202880,
        "moneyAfter": 199680,
        "type": "participation",
        "items": [
          {
            "item": "registry",
            "moneyCost": 500
          },
          {
            "item": "travel",
            "moneyCost": 1800
          },
          {
            "item": "hotel",
            "moneyCost": 900
          }
        ],
        "timestamp": "2024-02-09 05:37:36"
      },
      {
        "itemType": "tip",
        "item": "primeTipMedium:custom_195B277334903CE5-372",
        "inGameDate": "2024/5/25",
        "moneyBefore": 199680,
        "moneyCost": 80,
        "moneyAfter": 199600,
        "type": "purchase",
        "timestamp": "2024-02-09 05:58:20"
      },
      {
        "inGameDate": "2024/5/25",
        "year": 2024,
        "match": "space_grand_prix",
        "moneyBefore": 199600,
        "moneyAfter": 207600,
        "type": "championshipEarn",
        "items": {"TOP_16": {
          "actual": 8000,
          "raw": 10000
        }},
        "timestamp": "2024-02-10 01:04:40"
      },
      {
        "inGameDate": "2024/5/25",
        "moneyBefore": 207600,
        "moneyAfter": 205680,
        "type": "fees",
        "items": [{
          "item": "lifeFee",
          "moneyCost": 1920
        }],
        "timestamp": "2024-02-10 08:02:50"
      },
      {
        "item": 6,
        "inGameDate": "2024/6/18",
        "match": "custom_195B277334903CE5+2024+eight_master_tour_xian",
        "moneyBefore": 205680,
        "moneyAfter": 205880,
        "type": "invitation",
        "moneyEarn": 200,
        "timestamp": "2024-02-10 08:02:50"
      },
      {
        "inGameDate": "2024/6/18",
        "match": "custom_195B277334903CE5+2024+eight_master_tour_xian",
        "moneyBefore": 205880,
        "moneyAfter": 204880,
        "type": "participation",
        "items": [
          {
            "item": "registry",
            "moneyCost": 200
          },
          {
            "item": "travel",
            "moneyCost": 400
          },
          {
            "item": "hotel",
            "moneyCost": 400
          }
        ],
        "timestamp": "2024-02-10 08:02:50"
      },
      {
        "inGameDate": "2024/6/18",
        "year": 2024,
        "match": "eight_master_tour_xian",
        "moneyBefore": 204880,
        "moneyAfter": 228880,
        "type": "championshipEarn",
        "items": {"SECOND_PLACE": {
          "actual": 24000,
          "raw": 30000
        }},
        "timestamp": "2024-02-10 09:07:35"
      },
      {
        "inGameDate": "2024/6/18",
        "moneyBefore": 228880,
        "moneyAfter": 228080,
        "type": "fees",
        "items": [{
          "item": "lifeFee",
          "moneyCost": 800
        }],
        "timestamp": "2024-02-13 05:34:20"
      },
      {
        "inGameDate": "2024/6/28",
        "match": "custom_195B277334903CE5+2024+american_nine_sydney_burwood_cup",
        "moneyBefore": 228080,
        "moneyAfter": 227080,
        "type": "participation",
        "items": [
          {
            "item": "registry",
            "moneyCost": 200
          },
          {
            "item": "travel",
            "moneyCost": 400
          },
          {
            "item": "hotel",
            "moneyCost": 400
          }
        ],
        "timestamp": "2024-02-13 05:34:20"
      },
      {
        "inGameDate": "2024/6/28",
        "year": 2024,
        "match": "american_nine_sydney_burwood_cup",
        "moneyBefore": 227080,
        "moneyAfter": 243080,
        "type": "championshipEarn",
        "items": {"CHAMPION": {
          "actual": 16000,
          "raw": 20000
        }},
        "timestamp": "2024-02-13 06:23:42"
      },
      {
        "inGameDate": "2024/6/28",
        "perkUsed": 4,
        "moneyBefore": 243080,
        "moneyCost": 4100,
        "moneyAfter": 238980,
        "ability": {
          "rest": [
            94.99503717117187,
            96.49533494090156
          ],
          "powerControl": [
            84.01013625285964,
            85.44973080274525
          ],
          "antiHand": [
            82.05395340973637,
            83.57179527334691
          ],
          "spinControl": [
            93.01591168449833,
            94.0952752171184
          ]
        },
        "type": "upgrade",
        "timestamp": "2024-02-13 06:26:35"
      },
      {
        "inGameDate": "2024/6/28",
        "moneyBefore": 238980,
        "moneyAfter": 237900,
        "type": "fees",
        "items": [{
          "item": "lifeFee",
          "moneyCost": 1080
        }],
        "timestamp": "2024-02-13 06:26:37"
      },
      {
        "inGameDate": "2024/7/10",
        "match": "custom_195B277334903CE5+2024+chongqing_open",
        "moneyBefore": 237900,
        "moneyAfter": 236900,
        "type": "participation",
        "items": [
          {
            "item": "registry",
            "moneyCost": 200
          },
          {
            "item": "travel",
            "moneyCost": 400
          },
          {
            "item": "hotel",
            "moneyCost": 400
          }
        ],
        "timestamp": "2024-02-13 06:26:37"
      },
      {
        "inGameDate": "2024/7/10",
        "year": 2024,
        "match": "chongqing_open",
        "moneyBefore": 236900,
        "moneyAfter": 246500,
        "type": "championshipEarn",
        "items": {"TOP_4": {
          "actual": 9600,
          "raw": 12000
        }},
        "timestamp": "2024-02-16 06:35:18"
      },
      {
        "inGameDate": "2024/7/10",
        "perkUsed": 8,
        "moneyBefore": 246500,
        "moneyCost": 10400,
        "moneyAfter": 236100,
        "ability": {
          "rest": [
            96.49533494090156,
            97.90561484444747
          ],
          "powerControl": [
            85.44973080274525,
            86.83174157063544
          ],
          "cuePrecision": [
            97.96688089229359,
            98.84820565660185
          ],
          "spin": [
            99.15449457422577,
            99.98831479125674
          ],
          "antiHand": [
            83.57179527334691,
            86.42776652391652
          ],
          "spinControl": [
            94.0952752171184,
            95.13146420843367
          ],
          "aiming": [
            98.03797840517916,
            98.91645926897199
          ]
        },
        "type": "upgrade",
        "timestamp": "2024-02-16 06:36:05"
      },
      {
        "inGameDate": "2024/7/10",
        "moneyBefore": 236100,
        "moneyAfter": 235110,
        "type": "fees",
        "items": [{
          "item": "lifeFee",
          "moneyCost": 990
        }],
        "timestamp": "2024-02-16 06:36:56"
      },
      {
        "item": 6,
        "inGameDate": "2024/7/21",
        "match": "custom_195B277334903CE5+2024+eight_duck_goose_open",
        "moneyBefore": 235110,
        "moneyAfter": 235910,
        "type": "invitation",
        "moneyEarn": 800,
        "timestamp": "2024-02-16 06:36:56"
      },
      {
        "inGameDate": "2024/7/21",
        "match": "custom_195B277334903CE5+2024+eight_duck_goose_open",
        "moneyBefore": 235910,
        "moneyAfter": 233410,
        "type": "participation",
        "items": [
          {
            "item": "registry",
            "moneyCost": 200
          },
          {
            "item": "travel",
            "moneyCost": 1800
          },
          {
            "item": "hotel",
            "moneyCost": 500
          }
        ],
        "timestamp": "2024-02-16 06:36:56"
      },
      {
        "inGameDate": "2024/7/21",
        "year": 2024,
        "match": "eight_duck_goose_open",
        "moneyBefore": 233410,
        "moneyAfter": 234210,
        "type": "championshipEarn",
        "items": {"TOP_32": {
          "actual": 800,
          "raw": 1000
        }},
        "timestamp": "2024-02-16 07:06:55"
      }
    ],
    "level": 29,
    "expInThisLevel": 99,
    "availPerks": 0,
    "totalPerks": 125,
    "totalExp": 9635
  },
  "checksum": "C908E6DE267F62E2DA641FF2B0982743"
}