{"inventory": {
  "cueInstances": [
    {
      "tipId": "breakTip:Jack Lisowski-567",
      "instanceId": "stdBreakCue:Jack Lisowski-568",
      "creationTime": "2024-10-14 15:59:13",
      "customName": "开球杆:Jack Lisowski",
      "brand": "stdBreakCue",
      "lastSelectTime": "1970-01-01 10:00:00"
    },
    {
      "tipId": "stdTip:Jack Lisowski-569",
      "instanceId": "stdPoolCue:Jack Lisowski-570",
      "creationTime": "2024-10-14 15:59:13",
      "customName": "球房公杆-大头:Jack Lisowski",
      "brand": "stdPoolCue",
      "lastSelectTime": "1970-01-01 10:00:00"
    },
    {
      "tipId": "stdTip:Jack Lisowski-573",
      "instanceId": "profSnookerCue:Jack Lisowski-574",
      "creationTime": "2024-10-14 15:59:13",
      "customName": "进阶斯诺克杆:Jack Lisowski",
      "brand": "profSnookerCue",
      "lastSelectTime": "1970-01-01 10:00:00"
    },
    {
      "tipId": "stdTip:Jack Lisowski-571",
      "instanceId": "stdPottsCue:Jack Lisowski-572",
      "creationTime": "2024-10-14 15:59:13",
      "customName": "球房公杆-波茨:Jack Lisowski",
      "brand": "stdPottsCue",
      "lastSelectTime": "1970-01-01 10:00:00"
    },
    {
      "tipId": "stdTip:Jack Lisowski-565",
      "instanceId": "stdSnookerCue:Jack Lisowski-566",
      "creationTime": "2024-10-14 15:59:13",
      "customName": "球房公杆-小头:Jack Lisowski",
      "brand": "stdSnookerCue",
      "lastSelectTime": "1970-01-01 10:00:00"
    }
  ],
  "tips": {
    "stdTip:Jack Lisowski-571": {
      "totalHp": 587.7777777777778,
      "instanceId": "stdTip:Jack Lisowski-571",
      "diameter": 11.5,
      "hp": 587.7777777777778,
      "brand": "stdTip"
    },
    "stdTip:Jack Lisowski-573": {
      "totalHp": 401.1111111111111,
      "instanceId": "stdTip:Jack Lisowski-573",
      "diameter": 9.5,
      "hp": 401.1111111111111,
      "brand": "stdTip"
    },
    "breakTip:Jack Lisowski-567": {
      "totalHp": 5000,
      "instanceId": "breakTip:Jack Lisowski-567",
      "diameter": 15,
      "hp": 5000,
      "brand": "breakTip"
    },
    "stdTip:Jack Lisowski-565": {
      "totalHp": 401.1111111111111,
      "instanceId": "stdTip:Jack Lisowski-565",
      "diameter": 9.5,
      "hp": 401.1111111111111,
      "brand": "stdTip"
    },
    "stdTip:Jack Lisowski-569": {
      "totalHp": 810,
      "instanceId": "stdTip:Jack Lisowski-569",
      "diameter": 13.5,
      "hp": 810,
      "brand": "stdTip"
    }
  }
}}