{
  "players": {
    "Mang Zi": {
      "spin": 75,
      "precision": 60,
      "anglePrecision": 0.8,
      "longPrecision": 0.8,
      "name": "莽子",
      "maxPower": 100,
      "controllablePower": 86,
      "solving": 50,
      "pullDt": [
        100.0,
        250.0
      ],
      "aimingOffset": 0.2,
      "cuePlayType": "p2.5,h100,e500;l,l,r,r,r,l,l,l",
      "cueSwingMag": 50,
      "cuePointMuSigma": [
        15,
        50,
        0,
        30
      ],
      "powerControl": 80.0,
      "privateCues": [],
      "category": "Noob",
      "psy": 95,
      "height": 176,
      "width": 1.2,
      "hand": {
        "left": 20,
        "right": 100,
        "rest": 50
      },
      "ai": {
        "precision": 75,
        "stable": 75,
        "position": 80,
        "defense": 50,
        "attackPri": 99,
        "likeShow": 60,
        "snookerBreak": "right",
        "cebSideBreak": false,
        "withdrawAfter": 1
      }
    },
    "Lao Youtiao": {
      "spin": 91,
      "precision": 55,
      "anglePrecision": 1.2,
      "longPrecision": 0.7,
      "name": "老油条",
      "maxPower": 84,
      "controllablePower": 70,
      "solving": 70,
      "pullDt": [
        40.0,
        160.0
      ],
      "aimingOffset": -0.25,
      "cuePlayType": "p1.2,h300,e500;r,r,l,l,l,l,l",
      "cueSwingMag": 25,
      "cuePointMuSigma": [
        0,
        15,
        0,
        10
      ],
      "powerControl": 94.0,
      "privateCues": [],
      "category": "Amateur",
      "psy": 75,
      "height": 173,
      "width": 1.15,
      "hand": {
        "left": 70,
        "right": 100,
        "rest": 85
      },
      "ai": {
        "precision": 65,
        "stable": 95,
        "position": 85,
        "defense": 90,
        "attackPri": 50,
        "likeShow": 30,
        "snookerBreak": "right",
        "cebSideBreak": false,
        "withdrawAfter": 3
      }
    },
    "Mou Moumou": {
      "spin": 80,
      "precision": 80,
      "anglePrecision": 1,
      "longPrecision": 1,
      "name": "某某某",
      "maxPower": 88,
      "controllablePower": 72,
      "solving": 80,
      "pullDt": [
        40.0,
        180.0
      ],
      "aimingOffset": -0.15,
      "cuePlayType": "p1.2,h600,e500;l,l,l,r,r,r,r",
      "cueSwingMag": 20,
      "cuePointMuSigma": [
        0,
        15,
        0,
        10
      ],
      "powerControl": 95.0,
      "privateCues": [],
      "category": "Amateur",
      "psy": 80,
      "height": 176,
      "width": 1.0,
      "hand": {
        "left": 60,
        "right": 100,
        "rest": 80
      },
      "ai": {
        "precision": 80,
        "stable": 80,
        "position": 80,
        "defense": 80,
        "attackPri": 80,
        "likeShow": 40,
        "snookerBreak": "right",
        "cebSideBreak": false,
        "withdrawAfter": 2
      }
    },
    "Liu Mang": {
      "spin": 50,
      "precision": 98,
      "anglePrecision": 1.25,
      "longPrecision": 1.25,
      "name": "流氓",
      "maxPower": 100,
      "controllablePower": 80,
      "solving": 60,
      "pullDt": [
        50.0,
        200.0
      ],
      "aimingOffset": 0,
      "cuePlayType": "p1,h800,e500;s",
      "cueSwingMag": 0,
      "cuePointMuSigma": [
        0,
        0,
        0,
        5
      ],
      "powerControl": 85.0,
      "privateCues": [
        "AccurateGodCue"
      ],
      "category": "Amateur",
      "psy": 95,
      "height": 168,
      "width": 1.0,
      "hand": {
        "left": 100,
        "right": 60,
        "rest": 80
      },
      "ai": {
        "precision": 96.5,
        "stable": 70,
        "position": 50,
        "defense": 30,
        "attackPri": 99,
        "likeShow": 50,
        "snookerBreak": "right",
        "cebSideBreak": false,
        "withdrawAfter": 1
      }
    },
    "Mang Dali": {
      "spin": 100,
      "precision": 40,
      "anglePrecision": 0.7,
      "longPrecision": 0.6,
      "name": "莽大力",
      "maxPower": 100,
      "controllablePower": 98,
      "solving": 30,
      "pullDt": [
        80.0,
        250.0
      ],
      "aimingOffset": 0.35,
      "cuePlayType": "p1,h800,e500;s,s,s,s,s,l,l,l",
      "cueSwingMag": 25,
      "cuePointMuSigma": [
        0,
        15,
        0,
        1
      ],
      "powerControl": 95,
      "privateCues": [
        "MangCue"
      ],
      "category": "Amateur",
      "psy": 95,
      "height": 187,
      "width": 1.1,
      "hand": {
        "left": 10,
        "right": 100,
        "rest": 50
      },
      "ai": {
        "precision": 50,
        "stable": 60,
        "position": 95,
        "defense": 50,
        "attackPri": 99,
        "likeShow": 90,
        "snookerBreak": "right",
        "cebSideBreak": false,
        "withdrawAfter": 1
      }
    },
    "Noob": {
      "spin": 30,
      "precision": 30,
      "anglePrecision": 0.5,
      "longPrecision": 0.5,
      "name": "Noob",
      "maxPower": 65,
      "controllablePower": 42,
      "solving": 30,
      "pullDt": [
        30.0,
        150.0
      ],
      "aimingOffset": 0.4,
      "cuePlayType": "p1.5,h200,e400;r,r,l,l,l,l,l,l",
      "cueSwingMag": 80,
      "cuePointMuSigma": [
        -30,
        70,
        10,
        50
      ],
      "powerControl": 70.0,
      "privateCues": [],
      "category": "Noob",
      "psy": 50,
      "height": 175,
      "width": 1.0,
      "hand": {
        "left": 10,
        "right": 100,
        "rest": 40
      },
      "ai": {
        "precision": 30,
        "stable": 50,
        "position": 10,
        "defense": 10,
        "attackPri": 100,
        "likeShow": 50,
        "snookerBreak": "right",
        "cebSideBreak": false,
        "withdrawAfter": 0
      }
    },
    "Give Emperor": {
      "spin": 50,
      "precision": 70,
      "anglePrecision": 1.0,
      "longPrecision": 1.0,
      "name": "Give Emperor",
      "maxPower": 90,
      "controllablePower": 80,
      "solving": 80,
      "pullDt": [
        50.0,
        200.0
      ],
      "aimingOffset": 0.5,
      "cuePlayType": "p2,h1200,e500;r,r,r,r,r,r,l,l",
      "cueSwingMag": 15,
      "cuePointMuSigma": [
        -10,
        12,
        0,
        30
      ],
      "powerControl": 80,
      "privateCues": [],
      "category": "Amateur",
      "psy": 75,
      "height": 184,
      "width": 1.2,
      "hand": {
        "left": 100,
        "right": 90,
        "rest": 80
      },
      "ai": {
        "precision": 75,
        "stable": 90,
        "position": 100,
        "defense": 50,
        "attackPri": 90,
        "likeShow": 70,
        "snookerBreak": "left",
        "cebSideBreak": false,
        "withdrawAfter": 2
      }
    },
    "Baggage Brother": {
      "spin": 10,
      "precision": 70,
      "anglePrecision": 1.0,
      "longPrecision": 1.0,
      "name": "包弟",
      "maxPower": 75,
      "controllablePower": 45,
      "solving": 20,
      "pullDt": [
        80.0,
        180.0
      ],
      "aimingOffset": 0.0,
      "cuePlayType": "p3,h100,e1000;r,r,l,l,l,l,l,r",
      "cueSwingMag": 15,
      "cuePointMuSigma": [
        20,
        25,
        0,
        40
      ],
      "powerControl": 80,
      "privateCues": [],
      "category": "Amateur",
      "psy": 15,
      "height": 179,
      "width": 0.85,
      "hand": {
        "left": 10,
        "right": 100,
        "rest": 15
      },
      "ai": {
        "precision": 85,
        "stable": 30,
        "position": 35,
        "defense": 20,
        "attackPri": 100,
        "likeShow": 80,
        "snookerBreak": "left",
        "cebSideBreak": false,
        "withdrawAfter": 0
      }
    }
  }
}